{"v":"5.5.8","fr":30,"ip":0,"op":288,"w":271,"h":430,"nm":"anim-04","ddd":0,"assets":[],"layers":[{"ddd":0,"ind":1,"ty":3,"nm":"Null-screens","sr":1,"ks":{"o":{"a":0,"k":0,"ix":11},"r":{"a":0,"k":0,"ix":10},"p":{"a":1,"k":[{"i":{"x":0,"y":1},"o":{"x":0.509,"y":0},"t":83,"s":[-0.5,-1,0],"to":[-45.667,0,0],"ti":[45.667,0,0]},{"i":{"x":0,"y":0},"o":{"x":0.167,"y":0.167},"t":112,"s":[-274.5,-1,0],"to":[0,0,0],"ti":[0,0,0]},{"i":{"x":0,"y":1},"o":{"x":0.167,"y":0},"t":130,"s":[-274.5,-1,0],"to":[-47.5,0,0],"ti":[47.5,0,0]},{"i":{"x":0,"y":0},"o":{"x":0.167,"y":0.167},"t":160,"s":[-559.5,-1,0],"to":[0,0,0],"ti":[0,0,0]},{"i":{"x":0,"y":1},"o":{"x":0.167,"y":0},"t":243,"s":[-559.5,-1,0],"to":[93.167,0,0],"ti":[-93.167,0,0]},{"t":280,"s":[-0.5,-1,0]}],"ix":2},"a":{"a":0,"k":[0,0,0],"ix":1},"s":{"a":0,"k":[73,75,100],"ix":6}},"ao":0,"ip":0,"op":503,"st":0,"bm":0},{"ddd":0,"ind":2,"ty":4,"nm":"la3-08 Outlines","parent":1,"sr":1,"ks":{"o":{"a":1,"k":[{"i":{"x":[0.833],"y":[0.833]},"o":{"x":[0.167],"y":[0.167]},"t":173,"s":[0]},{"t":179,"s":[100]}],"ix":11},"r":{"a":0,"k":0,"ix":10},"p":{"a":0,"k":[951.172,254.685,0],"ix":2},"a":{"a":0,"k":[115.503,19.503,0],"ix":1},"s":{"a":0,"k":[136.986,133.333,100],"ix":6}},"ao":0,"shapes":[{"ty":"gr","it":[{"ind":0,"ty":"sh","ix":1,"ks":{"a":0,"k":{"i":[[0,0],[0,0],[0,0]],"o":[[0,0],[0,0],[0,0]],"v":[[-9.993,-0.176],[-3.214,6.604],[9.993,-6.604]],"c":false},"ix":2},"nm":"Path 1","mn":"ADBE Vector Shape - Group","hd":false},{"ty":"st","c":{"a":0,"k":[0,0,0,1],"ix":3},"o":{"a":0,"k":100,"ix":4},"w":{"a":0,"k":2.576,"ix":5},"lc":1,"lj":2,"bm":0,"nm":"Stroke 1","mn":"ADBE Vector Graphic - Stroke","hd":false},{"ty":"tr","p":{"a":0,"k":[212.518,19.678],"ix":2},"a":{"a":0,"k":[0,0],"ix":1},"s":{"a":0,"k":[100,100],"ix":3},"r":{"a":0,"k":0,"ix":6},"o":{"a":0,"k":100,"ix":7},"sk":{"a":0,"k":0,"ix":4},"sa":{"a":0,"k":0,"ix":5},"nm":"Transform"}],"nm":"Group 1","np":2,"cix":2,"bm":0,"ix":1,"mn":"ADBE Vector Group","hd":false},{"ty":"gr","it":[{"ind":0,"ty":"sh","ix":1,"ks":{"a":0,"k":{"i":[[4.001,0],[0,0],[0,4.001],[0,0],[-4.001,0],[0,0],[0,-4.001],[0,0]],"o":[[0,0],[-4.001,0],[0,0],[0,-4.001],[0,0],[4.001,0],[0,0],[0,4.001]],"v":[[108.008,19.253],[-108.01,19.253],[-115.253,12.008],[-115.253,-12.008],[-108.01,-19.253],[108.008,-19.253],[115.253,-12.008],[115.253,12.008]],"c":true},"ix":2},"nm":"Path 1","mn":"ADBE Vector Shape - Group","hd":false},{"ty":"fl","c":{"a":0,"k":[1,0.941000007181,0.250999989229,1],"ix":4},"o":{"a":0,"k":100,"ix":5},"r":1,"bm":0,"nm":"Fill 1","mn":"ADBE Vector Graphic - Fill","hd":false},{"ty":"tr","p":{"a":0,"k":[115.503,19.503],"ix":2},"a":{"a":0,"k":[0,0],"ix":1},"s":{"a":0,"k":[100,100],"ix":3},"r":{"a":0,"k":0,"ix":6},"o":{"a":0,"k":100,"ix":7},"sk":{"a":0,"k":0,"ix":4},"sa":{"a":0,"k":0,"ix":5},"nm":"Transform"}],"nm":"Group 2","np":2,"cix":2,"bm":0,"ix":2,"mn":"ADBE Vector Group","hd":false}],"ip":0,"op":503,"st":0,"bm":0},{"ddd":0,"ind":4,"ty":4,"nm":"la3-06 Outlines","parent":1,"sr":1,"ks":{"o":{"a":1,"k":[{"i":{"x":[0.833],"y":[0.833]},"o":{"x":[0.167],"y":[0.167]},"t":173,"s":[100]},{"t":179,"s":[0]}],"ix":11},"r":{"a":0,"k":0,"ix":10},"p":{"a":0,"k":[951.172,318.685,0],"ix":2},"a":{"a":0,"k":[115.503,19.503,0],"ix":1},"s":{"a":0,"k":[136.986,133.333,100],"ix":6}},"ao":0,"shapes":[{"ty":"gr","it":[{"ind":0,"ty":"sh","ix":1,"ks":{"a":0,"k":{"i":[[0,0],[0,0],[0,0]],"o":[[0,0],[0,0],[0,0]],"v":[[-9.993,-0.176],[-3.214,6.604],[9.993,-6.604]],"c":false},"ix":2},"nm":"Path 1","mn":"ADBE Vector Shape - Group","hd":false},{"ty":"st","c":{"a":0,"k":[0,0,0,1],"ix":3},"o":{"a":0,"k":100,"ix":4},"w":{"a":0,"k":2.576,"ix":5},"lc":1,"lj":2,"bm":0,"nm":"Stroke 1","mn":"ADBE Vector Graphic - Stroke","hd":false},{"ty":"tr","p":{"a":0,"k":[212.518,19.678],"ix":2},"a":{"a":0,"k":[0,0],"ix":1},"s":{"a":0,"k":[100,100],"ix":3},"r":{"a":0,"k":0,"ix":6},"o":{"a":0,"k":100,"ix":7},"sk":{"a":0,"k":0,"ix":4},"sa":{"a":0,"k":0,"ix":5},"nm":"Transform"}],"nm":"Group 1","np":2,"cix":2,"bm":0,"ix":1,"mn":"ADBE Vector Group","hd":false},{"ty":"gr","it":[{"ind":0,"ty":"sh","ix":1,"ks":{"a":0,"k":{"i":[[4.001,0],[0,0],[0,4.001],[0,0],[-4.001,0],[0,0],[0,-4.001],[0,0]],"o":[[0,0],[-4.001,0],[0,0],[0,-4.001],[0,0],[4.001,0],[0,0],[0,4.001]],"v":[[108.008,19.253],[-108.01,19.253],[-115.253,12.008],[-115.253,-12.008],[-108.01,-19.253],[108.008,-19.253],[115.253,-12.008],[115.253,12.008]],"c":true},"ix":2},"nm":"Path 1","mn":"ADBE Vector Shape - Group","hd":false},{"ty":"fl","c":{"a":0,"k":[1,0.941000007181,0.250999989229,1],"ix":4},"o":{"a":0,"k":100,"ix":5},"r":1,"bm":0,"nm":"Fill 1","mn":"ADBE Vector Graphic - Fill","hd":false},{"ty":"tr","p":{"a":0,"k":[115.503,19.503],"ix":2},"a":{"a":0,"k":[0,0],"ix":1},"s":{"a":0,"k":[100,100],"ix":3},"r":{"a":0,"k":0,"ix":6},"o":{"a":0,"k":100,"ix":7},"sk":{"a":0,"k":0,"ix":4},"sa":{"a":0,"k":0,"ix":5},"nm":"Transform"}],"nm":"Group 2","np":2,"cix":2,"bm":0,"ix":2,"mn":"ADBE Vector Group","hd":false}],"ip":0,"op":503,"st":0,"bm":0},{"ddd":0,"ind":6,"ty":4,"nm":"la3-07 Outlines","parent":1,"sr":1,"ks":{"o":{"a":1,"k":[{"i":{"x":[0.833],"y":[0.833]},"o":{"x":[0.167],"y":[0.167]},"t":173,"s":[0]},{"t":179,"s":[100]}],"ix":11},"r":{"a":0,"k":0,"ix":10},"p":{"a":0,"k":[951.172,319.001,0],"ix":2},"a":{"a":0,"k":[115.503,19.503,0],"ix":1},"s":{"a":0,"k":[136.986,133.333,100],"ix":6}},"ao":0,"shapes":[{"ty":"gr","it":[{"ind":0,"ty":"sh","ix":1,"ks":{"a":0,"k":{"i":[[4.001,0],[0,0],[0,-4.001],[0,0],[-4.002,0],[0,0],[0,4.001],[0,0]],"o":[[0,0],[-4.002,0],[0,0],[0,4.001],[0,0],[4.001,0],[0,0],[0,-4.001]],"v":[[108.008,-19.253],[-108.008,-19.253],[-115.253,-12.007],[-115.253,12.008],[-108.008,19.253],[108.008,19.253],[115.253,12.008],[115.253,-12.007]],"c":true},"ix":2},"nm":"Path 1","mn":"ADBE Vector Shape - Group","hd":false},{"ind":1,"ty":"sh","ix":2,"ks":{"a":0,"k":{"i":[[0,0],[0,-3.191],[0,0],[3.191,0],[0,0],[0,3.191],[0,0],[-3.191,0]],"o":[[3.191,0],[0,0],[0,3.191],[0,0],[-3.191,0],[0,0],[0,-3.191],[0,0]],"v":[[108.008,-17.794],[113.796,-12.007],[113.796,12.008],[108.008,17.795],[-108.008,17.795],[-113.796,12.008],[-113.796,-12.007],[-108.008,-17.794]],"c":true},"ix":2},"nm":"Path 2","mn":"ADBE Vector Shape - Group","hd":false},{"ty":"mm","mm":1,"nm":"Merge Paths 1","mn":"ADBE Vector Filter - Merge","hd":false},{"ty":"fl","c":{"a":0,"k":[0,0,0,1],"ix":4},"o":{"a":0,"k":100,"ix":5},"r":1,"bm":0,"nm":"Fill 1","mn":"ADBE Vector Graphic - Fill","hd":false},{"ty":"tr","p":{"a":0,"k":[115.503,19.502],"ix":2},"a":{"a":0,"k":[0,0],"ix":1},"s":{"a":0,"k":[100,100],"ix":3},"r":{"a":0,"k":0,"ix":6},"o":{"a":0,"k":100,"ix":7},"sk":{"a":0,"k":0,"ix":4},"sa":{"a":0,"k":0,"ix":5},"nm":"Transform"}],"nm":"Group 1","np":4,"cix":2,"bm":0,"ix":1,"mn":"ADBE Vector Group","hd":false},{"ty":"gr","it":[{"ind":0,"ty":"sh","ix":1,"ks":{"a":0,"k":{"i":[[0,0],[0,3.593],[0,0],[-3.593,0],[0,0],[0,-3.593],[0,0],[3.593,0]],"o":[[-3.593,0],[0,0],[0,-3.593],[0,0],[3.593,0],[0,0],[0,3.593],[0,0]],"v":[[-108.009,18.523],[-114.525,12.008],[-114.525,-12.007],[-108.009,-18.523],[108.009,-18.523],[114.525,-12.007],[114.525,12.008],[108.009,18.523]],"c":true},"ix":2},"nm":"Path 1","mn":"ADBE Vector Shape - Group","hd":false},{"ty":"fl","c":{"a":0,"k":[1,1,1,1],"ix":4},"o":{"a":0,"k":100,"ix":5},"r":1,"bm":0,"nm":"Fill 1","mn":"ADBE Vector Graphic - Fill","hd":false},{"ty":"tr","p":{"a":0,"k":[115.503,19.502],"ix":2},"a":{"a":0,"k":[0,0],"ix":1},"s":{"a":0,"k":[100,100],"ix":3},"r":{"a":0,"k":0,"ix":6},"o":{"a":0,"k":100,"ix":7},"sk":{"a":0,"k":0,"ix":4},"sa":{"a":0,"k":0,"ix":5},"nm":"Transform"}],"nm":"Group 2","np":2,"cix":2,"bm":0,"ix":2,"mn":"ADBE Vector Group","hd":false}],"ip":0,"op":503,"st":0,"bm":0},{"ddd":0,"ind":8,"ty":4,"nm":"la3-05 Outlines","parent":1,"sr":1,"ks":{"o":{"a":1,"k":[{"i":{"x":[0.833],"y":[0.833]},"o":{"x":[0.167],"y":[0.167]},"t":173,"s":[100]},{"t":179,"s":[0]}],"ix":11},"r":{"a":0,"k":0,"ix":10},"p":{"a":0,"k":[951.172,255.001,0],"ix":2},"a":{"a":0,"k":[115.503,19.503,0],"ix":1},"s":{"a":0,"k":[136.986,133.333,100],"ix":6}},"ao":0,"shapes":[{"ty":"gr","it":[{"ind":0,"ty":"sh","ix":1,"ks":{"a":0,"k":{"i":[[4.001,0],[0,0],[0,-4.001],[0,0],[-4.002,0],[0,0],[0,4.001],[0,0]],"o":[[0,0],[-4.002,0],[0,0],[0,4.001],[0,0],[4.001,0],[0,0],[0,-4.001]],"v":[[108.008,-19.253],[-108.008,-19.253],[-115.253,-12.007],[-115.253,12.008],[-108.008,19.253],[108.008,19.253],[115.253,12.008],[115.253,-12.007]],"c":true},"ix":2},"nm":"Path 1","mn":"ADBE Vector Shape - Group","hd":false},{"ind":1,"ty":"sh","ix":2,"ks":{"a":0,"k":{"i":[[0,0],[0,-3.191],[0,0],[3.191,0],[0,0],[0,3.191],[0,0],[-3.191,0]],"o":[[3.191,0],[0,0],[0,3.191],[0,0],[-3.191,0],[0,0],[0,-3.191],[0,0]],"v":[[108.008,-17.794],[113.796,-12.007],[113.796,12.008],[108.008,17.795],[-108.008,17.795],[-113.796,12.008],[-113.796,-12.007],[-108.008,-17.794]],"c":true},"ix":2},"nm":"Path 2","mn":"ADBE Vector Shape - Group","hd":false},{"ty":"mm","mm":1,"nm":"Merge Paths 1","mn":"ADBE Vector Filter - Merge","hd":false},{"ty":"fl","c":{"a":0,"k":[0,0,0,1],"ix":4},"o":{"a":0,"k":100,"ix":5},"r":1,"bm":0,"nm":"Fill 1","mn":"ADBE Vector Graphic - Fill","hd":false},{"ty":"tr","p":{"a":0,"k":[115.503,19.502],"ix":2},"a":{"a":0,"k":[0,0],"ix":1},"s":{"a":0,"k":[100,100],"ix":3},"r":{"a":0,"k":0,"ix":6},"o":{"a":0,"k":100,"ix":7},"sk":{"a":0,"k":0,"ix":4},"sa":{"a":0,"k":0,"ix":5},"nm":"Transform"}],"nm":"Group 1","np":4,"cix":2,"bm":0,"ix":1,"mn":"ADBE Vector Group","hd":false},{"ty":"gr","it":[{"ind":0,"ty":"sh","ix":1,"ks":{"a":0,"k":{"i":[[0,0],[0,3.593],[0,0],[-3.593,0],[0,0],[0,-3.593],[0,0],[3.593,0]],"o":[[-3.593,0],[0,0],[0,-3.593],[0,0],[3.593,0],[0,0],[0,3.593],[0,0]],"v":[[-108.009,18.523],[-114.525,12.008],[-114.525,-12.007],[-108.009,-18.523],[108.009,-18.523],[114.525,-12.007],[114.525,12.008],[108.009,18.523]],"c":true},"ix":2},"nm":"Path 1","mn":"ADBE Vector Shape - Group","hd":false},{"ty":"fl","c":{"a":0,"k":[1,1,1,1],"ix":4},"o":{"a":0,"k":100,"ix":5},"r":1,"bm":0,"nm":"Fill 1","mn":"ADBE Vector Graphic - Fill","hd":false},{"ty":"tr","p":{"a":0,"k":[115.503,19.502],"ix":2},"a":{"a":0,"k":[0,0],"ix":1},"s":{"a":0,"k":[100,100],"ix":3},"r":{"a":0,"k":0,"ix":6},"o":{"a":0,"k":100,"ix":7},"sk":{"a":0,"k":0,"ix":4},"sa":{"a":0,"k":0,"ix":5},"nm":"Transform"}],"nm":"Group 2","np":2,"cix":2,"bm":0,"ix":2,"mn":"ADBE Vector Group","hd":false}],"ip":0,"op":503,"st":0,"bm":0},{"ddd":0,"ind":10,"ty":4,"nm":"la3-btn-yell2","parent":1,"sr":1,"ks":{"o":{"a":1,"k":[{"i":{"x":[0.833],"y":[0.833]},"o":{"x":[0.167],"y":[0.167]},"t":2,"s":[0]},{"i":{"x":[0.833],"y":[0.833]},"o":{"x":[0.167],"y":[0.167]},"t":202,"s":[0]},{"t":207,"s":[100]}],"ix":11},"r":{"a":0,"k":0,"ix":10},"p":{"a":0,"k":[888.356,429.333,0],"ix":2},"a":{"a":0,"k":[20,24,0],"ix":1},"s":{"a":0,"k":[136.986,133.333,100],"ix":6}},"ao":0,"shapes":[{"ty":"gr","it":[{"ind":0,"ty":"sh","ix":1,"ks":{"a":0,"k":{"i":[[3.123,0],[0,0],[0,3.123],[0,0],[-3.123,0],[0,0],[0,-3.123],[0,0]],"o":[[0,0],[-3.123,0],[0,0],[0,-3.123],[0,0],[3.123,0],[0,0],[0,3.123]],"v":[[13.99,23.438],[-13.99,23.438],[-19.645,17.783],[-19.645,-17.783],[-13.99,-23.438],[13.99,-23.438],[19.645,-17.783],[19.645,17.783]],"c":true},"ix":2},"nm":"Path 1","mn":"ADBE Vector Shape - Group","hd":false},{"ty":"fl","c":{"a":0,"k":[1,0.941000007181,0.250999989229,1],"ix":4},"o":{"a":0,"k":100,"ix":5},"r":1,"bm":0,"nm":"Fill 1","mn":"ADBE Vector Graphic - Fill","hd":false},{"ty":"tr","p":{"a":0,"k":[19.895,23.687],"ix":2},"a":{"a":0,"k":[0,0],"ix":1},"s":{"a":0,"k":[100,100],"ix":3},"r":{"a":0,"k":0,"ix":6},"o":{"a":0,"k":100,"ix":7},"sk":{"a":0,"k":0,"ix":4},"sa":{"a":0,"k":0,"ix":5},"nm":"Transform"}],"nm":"Group 1","np":2,"cix":2,"bm":0,"ix":1,"mn":"ADBE Vector Group","hd":false}],"ip":0,"op":503,"st":0,"bm":0},{"ddd":0,"ind":11,"ty":4,"nm":"la3-btn-yell1 Outlines","parent":1,"sr":1,"ks":{"o":{"a":1,"k":[{"i":{"x":[0.833],"y":[0.833]},"o":{"x":[0.167],"y":[0.167]},"t":202,"s":[100]},{"t":207,"s":[0]}],"ix":11},"r":{"a":0,"k":0,"ix":10},"p":{"a":0,"k":[819.863,429.333,0],"ix":2},"a":{"a":0,"k":[20,24,0],"ix":1},"s":{"a":0,"k":[136.986,133.333,100],"ix":6}},"ao":0,"shapes":[{"ty":"gr","it":[{"ind":0,"ty":"sh","ix":1,"ks":{"a":0,"k":{"i":[[3.123,0],[0,0],[0,3.123],[0,0],[-3.123,0],[0,0],[0,-3.123],[0,0]],"o":[[0,0],[-3.123,0],[0,0],[0,-3.123],[0,0],[3.123,0],[0,0],[0,3.123]],"v":[[13.99,23.438],[-13.99,23.438],[-19.645,17.783],[-19.645,-17.783],[-13.99,-23.438],[13.99,-23.438],[19.645,-17.783],[19.645,17.783]],"c":true},"ix":2},"nm":"Path 1","mn":"ADBE Vector Shape - Group","hd":false},{"ty":"fl","c":{"a":0,"k":[1,0.941000007181,0.250999989229,1],"ix":4},"o":{"a":0,"k":100,"ix":5},"r":1,"bm":0,"nm":"Fill 1","mn":"ADBE Vector Graphic - Fill","hd":false},{"ty":"tr","p":{"a":0,"k":[19.895,23.687],"ix":2},"a":{"a":0,"k":[0,0],"ix":1},"s":{"a":0,"k":[100,100],"ix":3},"r":{"a":0,"k":0,"ix":6},"o":{"a":0,"k":100,"ix":7},"sk":{"a":0,"k":0,"ix":4},"sa":{"a":0,"k":0,"ix":5},"nm":"Transform"}],"nm":"Group 1","np":2,"cix":2,"bm":0,"ix":1,"mn":"ADBE Vector Group","hd":false}],"ip":0,"op":503,"st":0,"bm":0},{"ddd":0,"ind":12,"ty":4,"nm":"la3-btn-bottom2","parent":1,"sr":1,"ks":{"o":{"a":1,"k":[{"i":{"x":[0.833],"y":[0.833]},"o":{"x":[0.167],"y":[0.167]},"t":202,"s":[100]},{"t":207,"s":[0]}],"ix":11},"r":{"a":0,"k":0,"ix":10},"p":{"a":0,"k":[888.694,428.824,0],"ix":2},"a":{"a":0,"k":[19.894,23.688,0],"ix":1},"s":{"a":0,"k":[136.986,133.333,100],"ix":6}},"ao":0,"shapes":[{"ty":"gr","it":[{"ind":0,"ty":"sh","ix":1,"ks":{"a":0,"k":{"i":[[3.123,0],[0,0],[0,-3.123],[0,0],[-3.123,0],[0,0],[0,3.123],[0,0]],"o":[[0,0],[-3.123,0],[0,0],[0,3.123],[0,0],[3.123,0],[0,0],[0,-3.123]],"v":[[13.99,-23.438],[-13.99,-23.438],[-19.645,-17.783],[-19.645,17.783],[-13.99,23.438],[13.99,23.438],[19.645,17.783],[19.645,-17.783]],"c":true},"ix":2},"nm":"Path 1","mn":"ADBE Vector Shape - Group","hd":false},{"ind":1,"ty":"sh","ix":2,"ks":{"a":0,"k":{"i":[[0,0],[0,-2.315],[0,0],[2.314,0],[0,0],[0,2.314],[0,0],[-2.314,0]],"o":[[2.314,0],[0,0],[0,2.314],[0,0],[-2.314,0],[0,0],[0,-2.315],[0,0]],"v":[[13.99,-21.979],[18.186,-17.783],[18.186,17.783],[13.99,21.98],[-13.99,21.98],[-18.188,17.783],[-18.188,-17.783],[-13.99,-21.979]],"c":true},"ix":2},"nm":"Path 2","mn":"ADBE Vector Shape - Group","hd":false},{"ty":"mm","mm":1,"nm":"Merge Paths 1","mn":"ADBE Vector Filter - Merge","hd":false},{"ty":"fl","c":{"a":0,"k":[0,0,0,1],"ix":4},"o":{"a":0,"k":100,"ix":5},"r":1,"bm":0,"nm":"Fill 1","mn":"ADBE Vector Graphic - Fill","hd":false},{"ty":"tr","p":{"a":0,"k":[19.894,23.688],"ix":2},"a":{"a":0,"k":[0,0],"ix":1},"s":{"a":0,"k":[100,100],"ix":3},"r":{"a":0,"k":0,"ix":6},"o":{"a":0,"k":100,"ix":7},"sk":{"a":0,"k":0,"ix":4},"sa":{"a":0,"k":0,"ix":5},"nm":"Transform"}],"nm":"Group 1","np":4,"cix":2,"bm":0,"ix":1,"mn":"ADBE Vector Group","hd":false},{"ty":"gr","it":[{"ind":0,"ty":"sh","ix":1,"ks":{"a":0,"k":{"i":[[0,0],[0,2.716],[0,0],[-2.716,0],[0,0],[0,-2.716],[0,0],[2.716,0]],"o":[[-2.716,0],[0,0],[0,-2.716],[0,0],[2.716,0],[0,0],[0,2.716],[0,0]],"v":[[-13.99,22.708],[-18.915,17.784],[-18.915,-17.783],[-13.99,-22.708],[13.99,-22.708],[18.915,-17.783],[18.915,17.784],[13.99,22.708]],"c":true},"ix":2},"nm":"Path 1","mn":"ADBE Vector Shape - Group","hd":false},{"ty":"fl","c":{"a":0,"k":[1,1,1,1],"ix":4},"o":{"a":0,"k":100,"ix":5},"r":1,"bm":0,"nm":"Fill 1","mn":"ADBE Vector Graphic - Fill","hd":false},{"ty":"tr","p":{"a":0,"k":[19.895,23.687],"ix":2},"a":{"a":0,"k":[0,0],"ix":1},"s":{"a":0,"k":[100,100],"ix":3},"r":{"a":0,"k":0,"ix":6},"o":{"a":0,"k":100,"ix":7},"sk":{"a":0,"k":0,"ix":4},"sa":{"a":0,"k":0,"ix":5},"nm":"Transform"}],"nm":"Group 2","np":2,"cix":2,"bm":0,"ix":2,"mn":"ADBE Vector Group","hd":false}],"ip":0,"op":503,"st":0,"bm":0},{"ddd":0,"ind":13,"ty":4,"nm":"la3-btn-bottom1","parent":1,"sr":1,"ks":{"o":{"a":1,"k":[{"i":{"x":[0.833],"y":[0.833]},"o":{"x":[0.167],"y":[0.167]},"t":2,"s":[0]},{"i":{"x":[0.833],"y":[0.833]},"o":{"x":[0.167],"y":[0.167]},"t":202,"s":[0]},{"t":207,"s":[100]}],"ix":11},"r":{"a":0,"k":0,"ix":10},"p":{"a":0,"k":[820.2,428.824,0],"ix":2},"a":{"a":0,"k":[19.894,23.688,0],"ix":1},"s":{"a":0,"k":[136.986,133.333,100],"ix":6}},"ao":0,"shapes":[{"ty":"gr","it":[{"ind":0,"ty":"sh","ix":1,"ks":{"a":0,"k":{"i":[[3.123,0],[0,0],[0,-3.123],[0,0],[-3.123,0],[0,0],[0,3.123],[0,0]],"o":[[0,0],[-3.123,0],[0,0],[0,3.123],[0,0],[3.123,0],[0,0],[0,-3.123]],"v":[[13.99,-23.438],[-13.99,-23.438],[-19.645,-17.783],[-19.645,17.783],[-13.99,23.438],[13.99,23.438],[19.645,17.783],[19.645,-17.783]],"c":true},"ix":2},"nm":"Path 1","mn":"ADBE Vector Shape - Group","hd":false},{"ind":1,"ty":"sh","ix":2,"ks":{"a":0,"k":{"i":[[0,0],[0,-2.315],[0,0],[2.314,0],[0,0],[0,2.314],[0,0],[-2.314,0]],"o":[[2.314,0],[0,0],[0,2.314],[0,0],[-2.314,0],[0,0],[0,-2.315],[0,0]],"v":[[13.99,-21.979],[18.186,-17.783],[18.186,17.783],[13.99,21.98],[-13.99,21.98],[-18.188,17.783],[-18.188,-17.783],[-13.99,-21.979]],"c":true},"ix":2},"nm":"Path 2","mn":"ADBE Vector Shape - Group","hd":false},{"ty":"mm","mm":1,"nm":"Merge Paths 1","mn":"ADBE Vector Filter - Merge","hd":false},{"ty":"fl","c":{"a":0,"k":[0,0,0,1],"ix":4},"o":{"a":0,"k":100,"ix":5},"r":1,"bm":0,"nm":"Fill 1","mn":"ADBE Vector Graphic - Fill","hd":false},{"ty":"tr","p":{"a":0,"k":[19.894,23.688],"ix":2},"a":{"a":0,"k":[0,0],"ix":1},"s":{"a":0,"k":[100,100],"ix":3},"r":{"a":0,"k":0,"ix":6},"o":{"a":0,"k":100,"ix":7},"sk":{"a":0,"k":0,"ix":4},"sa":{"a":0,"k":0,"ix":5},"nm":"Transform"}],"nm":"Group 1","np":4,"cix":2,"bm":0,"ix":1,"mn":"ADBE Vector Group","hd":false},{"ty":"gr","it":[{"ind":0,"ty":"sh","ix":1,"ks":{"a":0,"k":{"i":[[0,0],[0,2.716],[0,0],[-2.716,0],[0,0],[0,-2.716],[0,0],[2.716,0]],"o":[[-2.716,0],[0,0],[0,-2.716],[0,0],[2.716,0],[0,0],[0,2.716],[0,0]],"v":[[-13.99,22.708],[-18.915,17.784],[-18.915,-17.783],[-13.99,-22.708],[13.99,-22.708],[18.915,-17.783],[18.915,17.784],[13.99,22.708]],"c":true},"ix":2},"nm":"Path 1","mn":"ADBE Vector Shape - Group","hd":false},{"ty":"fl","c":{"a":0,"k":[1,1,1,1],"ix":4},"o":{"a":0,"k":100,"ix":5},"r":1,"bm":0,"nm":"Fill 1","mn":"ADBE Vector Graphic - Fill","hd":false},{"ty":"tr","p":{"a":0,"k":[19.895,23.687],"ix":2},"a":{"a":0,"k":[0,0],"ix":1},"s":{"a":0,"k":[100,100],"ix":3},"r":{"a":0,"k":0,"ix":6},"o":{"a":0,"k":100,"ix":7},"sk":{"a":0,"k":0,"ix":4},"sa":{"a":0,"k":0,"ix":5},"nm":"Transform"}],"nm":"Group 2","np":2,"cix":2,"bm":0,"ix":2,"mn":"ADBE Vector Group","hd":false}],"ip":0,"op":503,"st":0,"bm":0},{"ddd":0,"ind":15,"ty":4,"nm":"la3-03 Outlines","parent":1,"sr":1,"ks":{"o":{"a":0,"k":0,"ix":11},"r":{"a":0,"k":0,"ix":10},"p":{"a":0,"k":[820.2,428.824,0],"ix":2},"a":{"a":0,"k":[19.894,23.688,0],"ix":1},"s":{"a":0,"k":[136.986,133.333,100],"ix":6}},"ao":0,"shapes":[{"ty":"gr","it":[{"ind":0,"ty":"sh","ix":1,"ks":{"a":0,"k":{"i":[[3.123,0],[0,0],[0,-3.123],[0,0],[-3.123,0],[0,0],[0,3.123],[0,0]],"o":[[0,0],[-3.123,0],[0,0],[0,3.123],[0,0],[3.123,0],[0,0],[0,-3.123]],"v":[[13.99,-23.438],[-13.99,-23.438],[-19.645,-17.783],[-19.645,17.783],[-13.99,23.438],[13.99,23.438],[19.645,17.783],[19.645,-17.783]],"c":true},"ix":2},"nm":"Path 1","mn":"ADBE Vector Shape - Group","hd":false},{"ind":1,"ty":"sh","ix":2,"ks":{"a":0,"k":{"i":[[0,0],[0,-2.315],[0,0],[2.314,0],[0,0],[0,2.314],[0,0],[-2.314,0]],"o":[[2.314,0],[0,0],[0,2.314],[0,0],[-2.314,0],[0,0],[0,-2.315],[0,0]],"v":[[13.99,-21.979],[18.186,-17.783],[18.186,17.783],[13.99,21.98],[-13.99,21.98],[-18.188,17.783],[-18.188,-17.783],[-13.99,-21.979]],"c":true},"ix":2},"nm":"Path 2","mn":"ADBE Vector Shape - Group","hd":false},{"ty":"mm","mm":1,"nm":"Merge Paths 1","mn":"ADBE Vector Filter - Merge","hd":false},{"ty":"fl","c":{"a":0,"k":[0,0,0,1],"ix":4},"o":{"a":0,"k":100,"ix":5},"r":1,"bm":0,"nm":"Fill 1","mn":"ADBE Vector Graphic - Fill","hd":false},{"ty":"tr","p":{"a":0,"k":[19.894,23.688],"ix":2},"a":{"a":0,"k":[0,0],"ix":1},"s":{"a":0,"k":[100,100],"ix":3},"r":{"a":0,"k":0,"ix":6},"o":{"a":0,"k":100,"ix":7},"sk":{"a":0,"k":0,"ix":4},"sa":{"a":0,"k":0,"ix":5},"nm":"Transform"}],"nm":"Group 1","np":4,"cix":2,"bm":0,"ix":1,"mn":"ADBE Vector Group","hd":false},{"ty":"gr","it":[{"ind":0,"ty":"sh","ix":1,"ks":{"a":0,"k":{"i":[[0,0],[0,2.716],[0,0],[-2.716,0],[0,0],[0,-2.716],[0,0],[2.716,0]],"o":[[-2.716,0],[0,0],[0,-2.716],[0,0],[2.716,0],[0,0],[0,2.716],[0,0]],"v":[[-13.99,22.708],[-18.915,17.784],[-18.915,-17.783],[-13.99,-22.708],[13.99,-22.708],[18.915,-17.783],[18.915,17.784],[13.99,22.708]],"c":true},"ix":2},"nm":"Path 1","mn":"ADBE Vector Shape - Group","hd":false},{"ty":"fl","c":{"a":0,"k":[1,1,1,1],"ix":4},"o":{"a":0,"k":100,"ix":5},"r":1,"bm":0,"nm":"Fill 1","mn":"ADBE Vector Graphic - Fill","hd":false},{"ty":"tr","p":{"a":0,"k":[19.895,23.687],"ix":2},"a":{"a":0,"k":[0,0],"ix":1},"s":{"a":0,"k":[100,100],"ix":3},"r":{"a":0,"k":0,"ix":6},"o":{"a":0,"k":100,"ix":7},"sk":{"a":0,"k":0,"ix":4},"sa":{"a":0,"k":0,"ix":5},"nm":"Transform"}],"nm":"Group 2","np":2,"cix":2,"bm":0,"ix":2,"mn":"ADBE Vector Group","hd":false}],"ip":0,"op":503,"st":0,"bm":0},{"ddd":0,"ind":17,"ty":4,"nm":"la3-save","parent":1,"sr":1,"ks":{"o":{"a":0,"k":100,"ix":11},"r":{"a":0,"k":0,"ix":10},"p":{"a":0,"k":[1077.788,536.409,0],"ix":2},"a":{"a":0,"k":[38.564,12.88,0],"ix":1},"s":{"a":1,"k":[{"i":{"x":[0.833,0.833,0.833],"y":[0.833,0.833,0.833]},"o":{"x":[0.167,0.167,0.167],"y":[0.167,0.167,0.167]},"t":202,"s":[0,133.333,100]},{"i":{"x":[0.833,0.833,0.833],"y":[0.833,0.833,0.833]},"o":{"x":[0.167,0.167,0.167],"y":[0.167,0.167,0.167]},"t":210,"s":[170,133.333,100]},{"i":{"x":[0.833,0.833,0.833],"y":[0.833,0.833,0.833]},"o":{"x":[0.167,0.167,0.167],"y":[0.167,0.167,0.167]},"t":215,"s":[136.986,133.333,100]},{"i":{"x":[0.833,0.833,0.833],"y":[0.833,0.833,0.833]},"o":{"x":[0.167,0.167,0.167],"y":[0.167,0.167,0.167]},"t":232,"s":[136.986,133.333,100]},{"i":{"x":[0.833,0.833,0.833],"y":[0.833,0.833,0.833]},"o":{"x":[0.167,0.167,0.167],"y":[0.167,0.167,0.167]},"t":236,"s":[170,133.333,100]},{"t":244,"s":[136.986,133.333,100]}],"ix":6}},"ao":0,"shapes":[{"ty":"gr","it":[{"ind":0,"ty":"sh","ix":1,"ks":{"a":0,"k":{"i":[[0,0],[0,0]],"o":[[0,0],[0,0]],"v":[[12.88,12.88],[64.248,12.88]],"c":false},"ix":2},"nm":"Path 1","mn":"ADBE Vector Shape - Group","hd":false},{"ty":"st","c":{"a":0,"k":[0,0,0,1],"ix":3},"o":{"a":0,"k":100,"ix":4},"w":{"a":0,"k":5.152,"ix":5},"lc":1,"lj":1,"ml":10,"bm":0,"nm":"Stroke 1","mn":"ADBE Vector Graphic - Stroke","hd":false},{"ty":"tr","p":{"a":0,"k":[0,0],"ix":2},"a":{"a":0,"k":[0,0],"ix":1},"s":{"a":0,"k":[100,100],"ix":3},"r":{"a":0,"k":0,"ix":6},"o":{"a":0,"k":100,"ix":7},"sk":{"a":0,"k":0,"ix":4},"sa":{"a":0,"k":0,"ix":5},"nm":"Transform"}],"nm":"Group 1","np":2,"cix":2,"bm":0,"ix":1,"mn":"ADBE Vector Group","hd":false}],"ip":0,"op":503,"st":0,"bm":0},{"ddd":0,"ind":19,"ty":4,"nm":"la3-02 Outlines","parent":1,"sr":1,"ks":{"o":{"a":0,"k":100,"ix":11},"r":{"a":0,"k":0,"ix":10},"p":{"a":0,"k":[828.473,536.409,0],"ix":2},"a":{"a":0,"k":[38.564,12.88,0],"ix":1},"s":{"a":0,"k":[136.986,133.333,100],"ix":6}},"ao":0,"shapes":[{"ty":"gr","it":[{"ind":0,"ty":"sh","ix":1,"ks":{"a":0,"k":{"i":[[0,0],[0,0]],"o":[[0,0],[0,0]],"v":[[12.88,12.88],[64.248,12.88]],"c":false},"ix":2},"nm":"Path 1","mn":"ADBE Vector Shape - Group","hd":false},{"ty":"st","c":{"a":0,"k":[0,0,0,1],"ix":3},"o":{"a":0,"k":100,"ix":4},"w":{"a":0,"k":5.152,"ix":5},"lc":1,"lj":1,"ml":10,"bm":0,"nm":"Stroke 1","mn":"ADBE Vector Graphic - Stroke","hd":false},{"ty":"tr","p":{"a":0,"k":[0,0],"ix":2},"a":{"a":0,"k":[0,0],"ix":1},"s":{"a":0,"k":[100,100],"ix":3},"r":{"a":0,"k":0,"ix":6},"o":{"a":0,"k":100,"ix":7},"sk":{"a":0,"k":0,"ix":4},"sa":{"a":0,"k":0,"ix":5},"nm":"Transform"}],"nm":"Group 1","np":2,"cix":2,"bm":0,"ix":1,"mn":"ADBE Vector Group","hd":false}],"ip":0,"op":503,"st":0,"bm":0},{"ddd":0,"ind":21,"ty":4,"nm":"la3-01 Outlines","parent":1,"sr":1,"ks":{"o":{"a":0,"k":100,"ix":11},"r":{"a":0,"k":0,"ix":10},"p":{"a":0,"k":[948.032,205.795,0],"ix":2},"a":{"a":0,"k":[142.713,132.808,0],"ix":1},"s":{"a":0,"k":[136.986,133.333,100],"ix":6}},"ao":0,"shapes":[{"ty":"gr","it":[{"ind":0,"ty":"sh","ix":1,"ks":{"a":0,"k":{"i":[[0,0],[0,0],[0,0],[0,0]],"o":[[0,0],[0,0],[0,0],[0,0]],"v":[[25.282,3.884],[-25.282,3.884],[-25.282,-3.884],[25.282,-3.884]],"c":true},"ix":2},"nm":"Path 1","mn":"ADBE Vector Shape - Group","hd":false},{"ty":"fl","c":{"a":0,"k":[0.8,0.8,0.8,1],"ix":4},"o":{"a":0,"k":100,"ix":5},"r":1,"bm":0,"nm":"Fill 1","mn":"ADBE Vector Graphic - Fill","hd":false},{"ty":"tr","p":{"a":0,"k":[100.607,31.313],"ix":2},"a":{"a":0,"k":[0,0],"ix":1},"s":{"a":0,"k":[100,100],"ix":3},"r":{"a":0,"k":0,"ix":6},"o":{"a":0,"k":100,"ix":7},"sk":{"a":0,"k":0,"ix":4},"sa":{"a":0,"k":0,"ix":5},"nm":"Transform"}],"nm":"Group 1","np":2,"cix":2,"bm":0,"ix":1,"mn":"ADBE Vector Group","hd":false},{"ty":"gr","it":[{"ind":0,"ty":"sh","ix":1,"ks":{"a":0,"k":{"i":[[0,0],[0,0],[0,0],[0,0]],"o":[[0,0],[0,0],[0,0],[0,0]],"v":[[40.501,3.884],[-40.502,3.884],[-40.502,-3.884],[40.501,-3.884]],"c":true},"ix":2},"nm":"Path 1","mn":"ADBE Vector Shape - Group","hd":false},{"ty":"fl","c":{"a":0,"k":[0.8,0.8,0.8,1],"ix":4},"o":{"a":0,"k":100,"ix":5},"r":1,"bm":0,"nm":"Fill 1","mn":"ADBE Vector Graphic - Fill","hd":false},{"ty":"tr","p":{"a":0,"k":[115.827,16.11],"ix":2},"a":{"a":0,"k":[0,0],"ix":1},"s":{"a":0,"k":[100,100],"ix":3},"r":{"a":0,"k":0,"ix":6},"o":{"a":0,"k":100,"ix":7},"sk":{"a":0,"k":0,"ix":4},"sa":{"a":0,"k":0,"ix":5},"nm":"Transform"}],"nm":"Group 2","np":2,"cix":2,"bm":0,"ix":2,"mn":"ADBE Vector Group","hd":false},{"ty":"gr","it":[{"ind":0,"ty":"sh","ix":1,"ks":{"a":0,"k":{"i":[[0,0],[0,0],[0,0],[0,0]],"o":[[0,0],[0,0],[0,0],[0,0]],"v":[[1.109,7.134],[-1.046,7.134],[-1.046,4.966],[1.109,4.966]],"c":true},"ix":2},"nm":"Path 1","mn":"ADBE Vector Shape - Group","hd":false},{"ind":1,"ty":"sh","ix":2,"ks":{"a":0,"k":{"i":[[0,0]],"o":[[0,0]],"v":[[1.109,4.965]],"c":false},"ix":2},"nm":"Path 2","mn":"ADBE Vector Shape - Group","hd":false},{"ind":2,"ty":"sh","ix":3,"ks":{"a":0,"k":{"i":[[-0.203,0.596],[-0.383,0.436],[-0.525,0.224],[-0.627,-0.007],[-0.535,-0.179],[-0.374,-0.336],[-0.19,-0.465],[0.011,-0.568],[0.104,-0.352],[0.163,-0.272],[0.202,-0.22],[0,0],[0,0],[0.166,-0.23],[0.094,-0.263],[-0.003,-0.308],[0,0],[0,0],[0,0],[-0.185,0.435],[-0.26,0.312],[-0.283,0.257],[-0.244,0.282],[-0.143,0.334],[0.034,0.416],[0.429,0.454],[0.612,-0.032],[0.379,-0.173],[0.23,-0.288],[0.092,-0.369],[-0.005,-0.425],[0,0]],"o":[[0.187,-0.551],[0.38,-0.427],[0.578,-0.243],[0.564,-0.008],[0.477,0.162],[0.371,0.34],[0.211,0.528],[0.004,0.367],[-0.093,0.303],[-0.155,0.254],[0,0],[0,0],[-0.2,0.2],[-0.16,0.228],[-0.103,0.29],[0,0],[0,0],[0,0],[0.014,-0.473],[0.167,-0.371],[0.247,-0.291],[0.277,-0.249],[0.239,-0.274],[0.151,-0.389],[-0.012,-0.624],[-0.449,-0.418],[-0.416,-0.01],[-0.331,0.164],[-0.233,0.301],[-0.106,0.412],[0,0],[-0.021,-0.628]],"v":[[-3.94,-4.285],[-3.076,-5.781],[-1.703,-6.769],[0.122,-7.126],[1.783,-6.866],[3.073,-6.111],[3.924,-4.889],[4.226,-3.228],[4.075,-2.144],[3.691,-1.279],[3.154,-0.566],[2.538,0.079],[1.92,0.669],[1.37,1.315],[0.986,2.056],[0.836,2.961],[0.836,3.716],[-0.77,3.716],[-0.77,2.797],[-0.468,1.424],[0.176,0.395],[0.973,-0.429],[1.755,-1.225],[2.331,-2.144],[2.51,-3.366],[1.824,-5.04],[0.163,-5.644],[-1.044,-5.397],[-1.895,-4.711],[-2.389,-3.695],[-2.54,-2.433],[-4.215,-2.433]],"c":true},"ix":2},"nm":"Path 3","mn":"ADBE Vector Shape - Group","hd":false},{"ty":"mm","mm":1,"nm":"Merge Paths 1","mn":"ADBE Vector Filter - Merge","hd":false},{"ty":"fl","c":{"a":0,"k":[0,0,0,1],"ix":4},"o":{"a":0,"k":100,"ix":5},"r":1,"bm":0,"nm":"Fill 1","mn":"ADBE Vector Graphic - Fill","hd":false},{"ty":"tr","p":{"a":0,"k":[243.73,20.689],"ix":2},"a":{"a":0,"k":[0,0],"ix":1},"s":{"a":0,"k":[100,100],"ix":3},"r":{"a":0,"k":0,"ix":6},"o":{"a":0,"k":100,"ix":7},"sk":{"a":0,"k":0,"ix":4},"sa":{"a":0,"k":0,"ix":5},"nm":"Transform"}],"nm":"Group 3","np":5,"cix":2,"bm":0,"ix":3,"mn":"ADBE Vector Group","hd":false},{"ty":"gr","it":[{"ind":0,"ty":"sh","ix":1,"ks":{"a":0,"k":{"i":[[0,0],[0.061,-8.338],[-8.338,-0.061],[-0.06,8.337],[0.001,0.073],[8.295,0.06]],"o":[[-8.338,-0.06],[-0.06,8.337],[8.338,0.06],[0.001,-0.074],[0,-8.296],[0,0]],"v":[[0.14,-14.988],[-15.067,0],[-0.079,15.206],[15.127,0.219],[15.127,0],[0.14,-15.097]],"c":true},"ix":2},"nm":"Path 1","mn":"ADBE Vector Shape - Group","hd":false},{"ind":1,"ty":"sh","ix":2,"ks":{"a":0,"k":{"i":[[9.053,-0.061],[0.06,9.095],[-9.095,0.06],[-0.06,-9.096],[0,-0.037]],"o":[[-9.096,0.06],[-0.061,-9.096],[9.096,-0.061],[0,0.037],[0,9.053]],"v":[[0.14,16.47],[-16.439,0.11],[-0.08,-16.469],[16.499,-0.11],[16.5,0]],"c":true},"ix":2},"nm":"Path 2","mn":"ADBE Vector Shape - Group","hd":false},{"ty":"mm","mm":1,"nm":"Merge Paths 1","mn":"ADBE Vector Filter - Merge","hd":false},{"ty":"fl","c":{"a":0,"k":[0,0,0,1],"ix":4},"o":{"a":0,"k":100,"ix":5},"r":1,"bm":0,"nm":"Fill 1","mn":"ADBE Vector Graphic - Fill","hd":false},{"ty":"tr","p":{"a":0,"k":[243.603,20.7],"ix":2},"a":{"a":0,"k":[0,0],"ix":1},"s":{"a":0,"k":[100,100],"ix":3},"r":{"a":0,"k":0,"ix":6},"o":{"a":0,"k":100,"ix":7},"sk":{"a":0,"k":0,"ix":4},"sa":{"a":0,"k":0,"ix":5},"nm":"Transform"}],"nm":"Group 4","np":4,"cix":2,"bm":0,"ix":4,"mn":"ADBE Vector Group","hd":false},{"ty":"gr","it":[{"ind":0,"ty":"sh","ix":1,"ks":{"a":0,"k":{"i":[[-1.408,-0.001],[-0.598,-0.248],[0.06,-2.114],[0,0],[0,0],[-1.285,0.136],[0,0],[0,0],[-1.927,0.81],[-0.633,-0.003],[-1.007,-0.997],[0,0],[0,0],[-0.828,1.015],[0,0],[0,0],[-1.904,2.065],[-1.431,-0.009],[0,0],[0,0],[0.137,1.285],[0,0],[0,0],[0.065,0.005],[0.048,2.807],[-1.02,0.98],[0,0],[0,0],[1.002,0.818],[0,0],[0,0],[1.408,0.002],[0.599,0.247],[-0.06,2.114],[0,0],[0,0],[0.663,0.001],[0.627,-0.065],[0,0],[0,0],[1.929,-0.811],[0.631,0.002],[1.007,0.994],[0,0],[0,0],[0.826,-1.015],[0,0],[0,0],[0.795,-1.966],[2.107,0.032],[0,0],[0,0],[-0.136,-1.285],[0,0],[0,0],[-0.07,-0.007],[0,0],[-0.773,-1.884],[1.525,-1.453],[0,0],[0,0],[-1.002,-0.818],[0,0],[0,0]],"o":[[0.647,-0.004],[1.943,0.834],[0,0],[0,0],[1.285,0.136],[0,0],[0,0],[-0.017,-2.09],[0.588,-0.238],[1.417,-0.015],[0,0],[0,0],[1.027,-0.813],[0,0],[0,0],[-2.064,-1.904],[0.971,-1.052],[0,0],[0,0],[0.137,-1.286],[0,0],[0,0],[-0.059,-0.03],[-2.808,0.048],[-0.024,-1.415],[0,0],[0,0],[-0.805,-1.012],[0,0],[0,0],[-0.992,0.999],[-0.647,0.004],[-1.943,-0.835],[0,0],[0,0],[-0.659,-0.073],[-0.63,0],[0,0],[0,0],[0.02,2.093],[-0.586,0.237],[-1.415,0.016],[0,0],[0,0],[-1.025,0.814],[0,0],[0,0],[1.553,1.446],[-0.866,1.921],[0,0],[0,0],[-0.136,1.286],[0,0],[0,0],[0.063,0.031],[0,0],[2.037,0.03],[0.782,1.956],[0,0],[0,0],[0.806,1.012],[0,0],[0,0],[0.992,-1]],"v":[[-7.298,12.591],[-5.41,12.959],[-2.291,17.843],[-2.291,18.139],[-1.995,18.173],[1.871,18.173],[2.161,18.173],[2.161,17.876],[5.319,13.081],[7.168,12.726],[10.957,14.26],[11.157,14.473],[11.389,14.292],[14.179,11.541],[14.366,11.309],[14.147,11.104],[13.856,3.919],[17.627,2.281],[18.103,2.281],[18.136,1.985],[18.136,-1.882],[18.136,-2.062],[17.975,-2.139],[17.788,-2.191],[12.617,-7.187],[14.179,-10.942],[14.392,-11.148],[14.205,-11.38],[11.486,-14.132],[11.254,-14.318],[11.048,-14.098],[7.297,-12.54],[5.409,-12.907],[2.29,-17.792],[2.29,-18.088],[1.994,-18.12],[0.009,-18.23],[-1.879,-18.133],[-2.169,-18.133],[-2.169,-17.837],[-5.326,-13.036],[-7.169,-12.68],[-10.952,-14.209],[-11.158,-14.422],[-11.39,-14.241],[-14.174,-11.49],[-14.36,-11.258],[-14.142,-11.051],[-12.885,-5.387],[-17.782,-2.275],[-18.066,-2.275],[-18.066,-1.992],[-18.066,1.876],[-18.066,2.055],[-17.905,2.133],[-17.705,2.191],[-17.576,2.191],[-12.943,5.348],[-14.174,10.993],[-14.386,11.199],[-14.206,11.432],[-11.486,14.183],[-11.255,14.37],[-11.048,14.152]],"c":true},"ix":2},"nm":"Path 1","mn":"ADBE Vector Shape - Group","hd":false},{"ind":1,"ty":"sh","ix":2,"ks":{"a":0,"k":{"i":[[0.719,0.002],[0.764,0.09],[-0.058,1.019],[1.329,0.547],[0.415,-0.004],[0.674,-0.701],[0.796,0.64],[0.927,1.191],[-0.743,0.683],[0.527,1.307],[1.335,0.026],[0,0],[0.198,1.013],[-0.17,1.499],[-0.992,-0.026],[-0.617,1.307],[1.058,0.955],[-0.636,0.796],[-1.194,0.947],[-0.681,-0.745],[-0.971,0.006],[-0.377,0.15],[0.042,1.399],[-1.004,0.11],[-1.499,-0.171],[0.057,-1.021],[-1.315,-0.566],[-0.416,0.004],[-0.676,0.699],[-0.797,-0.635],[-0.928,-1.192],[0.743,-0.683],[-1.239,-1.374],[-0.968,0.016],[-0.184,-1.005],[0.17,-1.499],[0.986,0.007],[0,0],[0.535,-1.238],[-1.057,-0.955],[0.641,-0.797],[1.193,-0.947],[0.433,0],[0.361,0.404],[0.971,-0.003],[0.376,-0.149],[-0.043,-1.4],[1.004,-0.111]],"o":[[-0.769,-0.001],[-1.014,-0.121],[0.084,-1.435],[-0.385,-0.157],[-0.972,-0.005],[-0.688,0.756],[-1.172,-0.951],[-0.623,-0.794],[1.038,-0.952],[-0.502,-1.237],[0,0],[-1.032,0.029],[-0.17,-1.499],[0.097,-0.988],[1.444,0.065],[0.548,-1.316],[-0.752,-0.687],[0.947,-1.193],[0.796,-0.621],[0.677,0.697],[0.406,0.005],[1.291,-0.541],[-0.034,-1.01],[1.499,-0.171],[1.017,0.117],[-0.101,1.43],[0.385,0.157],[0.971,0.007],[0.685,-0.754],[1.174,0.95],[0.622,0.794],[-1.374,1.24],[0.649,0.719],[1.021,-0.016],[0.17,1.499],[-0.116,0.978],[0,0],[-1.349,0.012],[-0.548,1.316],[0.757,0.688],[-0.947,1.194],[-0.341,0.267],[-0.542,-0.006],[-0.677,-0.696],[-0.406,-0.004],[-1.293,0.54],[0.034,1.01],[-0.715,0.075]],"v":[[0.003,20.002],[-2.298,19.867],[-3.999,17.837],[-6.08,14.524],[-7.292,14.292],[-9.869,15.382],[-12.511,15.588],[-15.669,12.365],[-15.456,9.749],[-14.606,5.993],[-17.634,3.911],[-17.712,3.911],[-19.844,2.204],[-19.844,-2.307],[-17.911,-4.014],[-14.509,-6.064],[-15.36,-9.853],[-15.566,-12.489],[-12.344,-15.71],[-9.728,-15.491],[-7.15,-14.409],[-5.964,-14.628],[-3.889,-17.848],[-2.169,-19.834],[2.342,-19.834],[4.05,-17.805],[6.079,-14.473],[7.291,-14.241],[9.869,-15.324],[12.504,-15.536],[15.668,-12.314],[15.455,-9.697],[15.212,-4.965],[17.756,-3.86],[19.844,-2.146],[19.844,2.365],[17.91,4.072],[17.588,4.072],[14.489,6.128],[15.339,9.917],[15.545,12.559],[12.324,15.781],[11.131,16.193],[9.714,15.549],[7.136,14.466],[5.951,14.686],[3.875,17.907],[2.155,19.893]],"c":true},"ix":2},"nm":"Path 2","mn":"ADBE Vector Shape - Group","hd":false},{"ty":"mm","mm":1,"nm":"Merge Paths 1","mn":"ADBE Vector Filter - Merge","hd":false},{"ty":"fl","c":{"a":0,"k":[0,0,0,1],"ix":4},"o":{"a":0,"k":100,"ix":5},"r":1,"bm":0,"nm":"Fill 1","mn":"ADBE Vector Graphic - Fill","hd":false},{"ty":"tr","p":{"a":0,"k":[42.91,20.255],"ix":2},"a":{"a":0,"k":[0,0],"ix":1},"s":{"a":0,"k":[100,100],"ix":3},"r":{"a":0,"k":0,"ix":6},"o":{"a":0,"k":100,"ix":7},"sk":{"a":0,"k":0,"ix":4},"sa":{"a":0,"k":0,"ix":5},"nm":"Transform"}],"nm":"Group 5","np":4,"cix":2,"bm":0,"ix":5,"mn":"ADBE Vector Group","hd":false},{"ty":"gr","it":[{"ind":0,"ty":"sh","ix":1,"ks":{"a":0,"k":{"i":[[3.511,-0.004],[0,3.512],[-3.513,0],[0,-3.513]],"o":[[-3.513,0],[0,-3.513],[3.513,0],[-0.004,3.511]],"v":[[0,6.36],[-6.36,0.001],[0,-6.359],[6.36,0.001]],"c":true},"ix":2},"nm":"Path 1","mn":"ADBE Vector Shape - Group","hd":false},{"ind":1,"ty":"sh","ix":2,"ks":{"a":0,"k":{"i":[[4.447,0.003],[0,-4.449],[-4.449,0],[0,4.448]],"o":[[-4.449,0],[0,4.448],[4.449,0],[-0.004,-4.448]],"v":[[0,-8.054],[-8.055,0.001],[0,8.054],[8.055,0.001]],"c":true},"ix":2},"nm":"Path 2","mn":"ADBE Vector Shape - Group","hd":false},{"ty":"mm","mm":1,"nm":"Merge Paths 1","mn":"ADBE Vector Filter - Merge","hd":false},{"ty":"fl","c":{"a":0,"k":[0,0,0,1],"ix":4},"o":{"a":0,"k":100,"ix":5},"r":1,"bm":0,"nm":"Fill 1","mn":"ADBE Vector Graphic - Fill","hd":false},{"ty":"tr","p":{"a":0,"k":[42.913,20.28],"ix":2},"a":{"a":0,"k":[0,0],"ix":1},"s":{"a":0,"k":[100,100],"ix":3},"r":{"a":0,"k":0,"ix":6},"o":{"a":0,"k":100,"ix":7},"sk":{"a":0,"k":0,"ix":4},"sa":{"a":0,"k":0,"ix":5},"nm":"Transform"}],"nm":"Group 6","np":4,"cix":2,"bm":0,"ix":6,"mn":"ADBE Vector Group","hd":false},{"ty":"gr","it":[{"ind":0,"ty":"sh","ix":1,"ks":{"a":0,"k":{"i":[[0,0],[0,0],[0,0],[0,0]],"o":[[0,0],[0,0],[0,0],[0,0]],"v":[[44.897,5.656],[-44.897,5.656],[-44.897,-5.657],[44.897,-5.657]],"c":true},"ix":2},"nm":"Path 1","mn":"ADBE Vector Shape - Group","hd":false},{"ty":"fl","c":{"a":0,"k":[0.8,0.8,0.8,1],"ix":4},"o":{"a":0,"k":100,"ix":5},"r":1,"bm":0,"nm":"Fill 1","mn":"ADBE Vector Graphic - Fill","hd":false},{"ty":"tr","p":{"a":0,"k":[74.648,259.709],"ix":2},"a":{"a":0,"k":[0,0],"ix":1},"s":{"a":0,"k":[100,100],"ix":3},"r":{"a":0,"k":0,"ix":6},"o":{"a":0,"k":100,"ix":7},"sk":{"a":0,"k":0,"ix":4},"sa":{"a":0,"k":0,"ix":5},"nm":"Transform"}],"nm":"Group 7","np":2,"cix":2,"bm":0,"ix":7,"mn":"ADBE Vector Group","hd":false},{"ty":"gr","it":[{"ind":0,"ty":"sh","ix":1,"ks":{"a":0,"k":{"i":[[0,0],[0,0],[0,0],[0,0]],"o":[[0,0],[0,0],[0,0],[0,0]],"v":[[83.163,5.656],[-83.163,5.656],[-83.163,-5.656],[83.163,-5.656]],"c":true},"ix":2},"nm":"Path 1","mn":"ADBE Vector Shape - Group","hd":false},{"ty":"fl","c":{"a":0,"k":[0.8,0.8,0.8,1],"ix":4},"o":{"a":0,"k":100,"ix":5},"r":1,"bm":0,"nm":"Fill 1","mn":"ADBE Vector Graphic - Fill","hd":false},{"ty":"tr","p":{"a":0,"k":[112.913,133.132],"ix":2},"a":{"a":0,"k":[0,0],"ix":1},"s":{"a":0,"k":[100,100],"ix":3},"r":{"a":0,"k":0,"ix":6},"o":{"a":0,"k":100,"ix":7},"sk":{"a":0,"k":0,"ix":4},"sa":{"a":0,"k":0,"ix":5},"nm":"Transform"}],"nm":"Group 8","np":2,"cix":2,"bm":0,"ix":8,"mn":"ADBE Vector Group","hd":false},{"ty":"gr","it":[{"ind":0,"ty":"sh","ix":1,"ks":{"a":0,"k":{"i":[[0,0],[0,0],[0,0],[0,0]],"o":[[0,0],[0,0],[0,0],[0,0]],"v":[[115.254,5.656],[-115.254,5.656],[-115.254,-5.656],[115.254,-5.656]],"c":true},"ix":2},"nm":"Path 1","mn":"ADBE Vector Shape - Group","hd":false},{"ty":"fl","c":{"a":0,"k":[0.8,0.8,0.8,1],"ix":4},"o":{"a":0,"k":100,"ix":5},"r":1,"bm":0,"nm":"Fill 1","mn":"ADBE Vector Graphic - Fill","hd":false},{"ty":"tr","p":{"a":0,"k":[145.004,112.75],"ix":2},"a":{"a":0,"k":[0,0],"ix":1},"s":{"a":0,"k":[100,100],"ix":3},"r":{"a":0,"k":0,"ix":6},"o":{"a":0,"k":100,"ix":7},"sk":{"a":0,"k":0,"ix":4},"sa":{"a":0,"k":0,"ix":5},"nm":"Transform"}],"nm":"Group 9","np":2,"cix":2,"bm":0,"ix":9,"mn":"ADBE Vector Group","hd":false},{"ty":"gr","it":[{"ind":0,"ty":"sh","ix":1,"ks":{"a":0,"k":{"i":[[0,0],[0,0]],"o":[[0,0],[0,0]],"v":[[7.285,84.114],[278.14,84.114]],"c":false},"ix":2},"nm":"Path 1","mn":"ADBE Vector Shape - Group","hd":false},{"ty":"st","c":{"a":0,"k":[1,0.941000007181,0.250999989229,1],"ix":3},"o":{"a":0,"k":100,"ix":4},"w":{"a":0,"k":2.914,"ix":5},"lc":1,"lj":1,"ml":10,"bm":0,"nm":"Stroke 1","mn":"ADBE Vector Graphic - Stroke","hd":false},{"ty":"tr","p":{"a":0,"k":[0,0],"ix":2},"a":{"a":0,"k":[0,0],"ix":1},"s":{"a":0,"k":[100,100],"ix":3},"r":{"a":0,"k":0,"ix":6},"o":{"a":0,"k":100,"ix":7},"sk":{"a":0,"k":0,"ix":4},"sa":{"a":0,"k":0,"ix":5},"nm":"Transform"}],"nm":"Group 10","np":2,"cix":2,"bm":0,"ix":10,"mn":"ADBE Vector Group","hd":false}],"ip":0,"op":503,"st":0,"bm":0},{"ddd":0,"ind":23,"ty":4,"nm":"la2-08 Outlines","parent":1,"sr":1,"ks":{"o":{"a":0,"k":100,"ix":11},"r":{"a":0,"k":0,"ix":10},"p":{"a":0,"k":[562.838,439.669,0],"ix":2},"a":{"a":0,"k":[115.503,19.503,0],"ix":1},"s":{"a":0,"k":[136.986,133.333,100],"ix":6}},"ao":0,"shapes":[{"ty":"gr","it":[{"ind":0,"ty":"sh","ix":1,"ks":{"a":0,"k":{"i":[[0,0],[0,0],[0,0]],"o":[[0,0],[0,0],[0,0]],"v":[[-3.87,-8.351],[3.981,-0.5],[-3.982,8.351]],"c":false},"ix":2},"nm":"Path 1","mn":"ADBE Vector Shape - Group","hd":false},{"ty":"st","c":{"a":0,"k":[0,0,0,1],"ix":3},"o":{"a":0,"k":100,"ix":4},"w":{"a":0,"k":1.663,"ix":5},"lc":1,"lj":1,"ml":10,"bm":0,"nm":"Stroke 1","mn":"ADBE Vector Graphic - Stroke","hd":false},{"ty":"tr","p":{"a":0,"k":[213.974,18.799],"ix":2},"a":{"a":0,"k":[0,0],"ix":1},"s":{"a":0,"k":[100,100],"ix":3},"r":{"a":0,"k":0,"ix":6},"o":{"a":0,"k":100,"ix":7},"sk":{"a":0,"k":0,"ix":4},"sa":{"a":0,"k":0,"ix":5},"nm":"Transform"}],"nm":"Group 1","np":2,"cix":2,"bm":0,"ix":1,"mn":"ADBE Vector Group","hd":false},{"ty":"gr","it":[{"ind":0,"ty":"sh","ix":1,"ks":{"a":0,"k":{"i":[[4.001,0],[0,0],[0,-4.001],[0,0],[-4.001,0],[0,0],[0,4.001],[0,0]],"o":[[0,0],[-4.001,0],[0,0],[0,4.001],[0,0],[4.001,0],[0,0],[0,-4.001]],"v":[[108.008,-19.253],[-108.01,-19.253],[-115.253,-12.007],[-115.253,12.008],[-108.01,19.253],[108.008,19.253],[115.253,12.008],[115.253,-12.007]],"c":true},"ix":2},"nm":"Path 1","mn":"ADBE Vector Shape - Group","hd":false},{"ind":1,"ty":"sh","ix":2,"ks":{"a":0,"k":{"i":[[0,0],[0,-3.191],[0,0],[3.191,0],[0,0],[0,3.191],[0,0],[-3.19,0]],"o":[[3.191,0],[0,0],[0,3.191],[0,0],[-3.19,0],[0,0],[0,-3.191],[0,0]],"v":[[108.008,-17.794],[113.796,-12.007],[113.796,12.008],[108.008,17.795],[-108.01,17.795],[-113.796,12.008],[-113.796,-12.007],[-108.01,-17.794]],"c":true},"ix":2},"nm":"Path 2","mn":"ADBE Vector Shape - Group","hd":false},{"ty":"mm","mm":1,"nm":"Merge Paths 1","mn":"ADBE Vector Filter - Merge","hd":false},{"ty":"fl","c":{"a":0,"k":[0,0,0,1],"ix":4},"o":{"a":0,"k":100,"ix":5},"r":1,"bm":0,"nm":"Fill 1","mn":"ADBE Vector Graphic - Fill","hd":false},{"ty":"tr","p":{"a":0,"k":[115.503,19.503],"ix":2},"a":{"a":0,"k":[0,0],"ix":1},"s":{"a":0,"k":[100,100],"ix":3},"r":{"a":0,"k":0,"ix":6},"o":{"a":0,"k":100,"ix":7},"sk":{"a":0,"k":0,"ix":4},"sa":{"a":0,"k":0,"ix":5},"nm":"Transform"}],"nm":"Group 2","np":4,"cix":2,"bm":0,"ix":2,"mn":"ADBE Vector Group","hd":false},{"ty":"gr","it":[{"ind":0,"ty":"sh","ix":1,"ks":{"a":0,"k":{"i":[[0,0],[0,3.593],[0,0],[-3.593,0],[0,0],[0,-3.593],[0,0],[3.593,0]],"o":[[-3.593,0],[0,0],[0,-3.593],[0,0],[3.593,0],[0,0],[0,3.593],[0,0]],"v":[[-108.009,18.523],[-114.525,12.008],[-114.525,-12.007],[-108.009,-18.523],[108.009,-18.523],[114.525,-12.007],[114.525,12.008],[108.009,18.523]],"c":true},"ix":2},"nm":"Path 1","mn":"ADBE Vector Shape - Group","hd":false},{"ty":"fl","c":{"a":0,"k":[1,1,1,1],"ix":4},"o":{"a":0,"k":100,"ix":5},"r":1,"bm":0,"nm":"Fill 1","mn":"ADBE Vector Graphic - Fill","hd":false},{"ty":"tr","p":{"a":0,"k":[115.503,19.502],"ix":2},"a":{"a":0,"k":[0,0],"ix":1},"s":{"a":0,"k":[100,100],"ix":3},"r":{"a":0,"k":0,"ix":6},"o":{"a":0,"k":100,"ix":7},"sk":{"a":0,"k":0,"ix":4},"sa":{"a":0,"k":0,"ix":5},"nm":"Transform"}],"nm":"Group 3","np":2,"cix":2,"bm":0,"ix":3,"mn":"ADBE Vector Group","hd":false}],"ip":0,"op":503,"st":0,"bm":0},{"ddd":0,"ind":25,"ty":4,"nm":"la2-06 Outlines","parent":1,"sr":1,"ks":{"o":{"a":0,"k":100,"ix":11},"r":{"a":0,"k":0,"ix":10},"p":{"a":0,"k":[562.838,334.335,0],"ix":2},"a":{"a":0,"k":[115.503,19.503,0],"ix":1},"s":{"a":0,"k":[136.986,133.333,100],"ix":6}},"ao":0,"shapes":[{"ty":"gr","it":[{"ind":0,"ty":"sh","ix":1,"ks":{"a":0,"k":{"i":[[0,0],[0,0],[0,0]],"o":[[0,0],[0,0],[0,0]],"v":[[-3.87,-8.351],[3.981,-0.5],[-3.982,8.351]],"c":false},"ix":2},"nm":"Path 1","mn":"ADBE Vector Shape - Group","hd":false},{"ty":"st","c":{"a":0,"k":[0,0,0,1],"ix":3},"o":{"a":0,"k":100,"ix":4},"w":{"a":0,"k":1.663,"ix":5},"lc":1,"lj":1,"ml":10,"bm":0,"nm":"Stroke 1","mn":"ADBE Vector Graphic - Stroke","hd":false},{"ty":"tr","p":{"a":0,"k":[213.974,18.799],"ix":2},"a":{"a":0,"k":[0,0],"ix":1},"s":{"a":0,"k":[100,100],"ix":3},"r":{"a":0,"k":0,"ix":6},"o":{"a":0,"k":100,"ix":7},"sk":{"a":0,"k":0,"ix":4},"sa":{"a":0,"k":0,"ix":5},"nm":"Transform"}],"nm":"Group 1","np":2,"cix":2,"bm":0,"ix":1,"mn":"ADBE Vector Group","hd":false},{"ty":"gr","it":[{"ind":0,"ty":"sh","ix":1,"ks":{"a":0,"k":{"i":[[4.001,0],[0,0],[0,-4.001],[0,0],[-4.001,0],[0,0],[0,4.001],[0,0]],"o":[[0,0],[-4.001,0],[0,0],[0,4.001],[0,0],[4.001,0],[0,0],[0,-4.001]],"v":[[108.008,-19.253],[-108.01,-19.253],[-115.253,-12.007],[-115.253,12.008],[-108.01,19.253],[108.008,19.253],[115.253,12.008],[115.253,-12.007]],"c":true},"ix":2},"nm":"Path 1","mn":"ADBE Vector Shape - Group","hd":false},{"ind":1,"ty":"sh","ix":2,"ks":{"a":0,"k":{"i":[[0,0],[0,-3.191],[0,0],[3.191,0],[0,0],[0,3.191],[0,0],[-3.19,0]],"o":[[3.191,0],[0,0],[0,3.191],[0,0],[-3.19,0],[0,0],[0,-3.191],[0,0]],"v":[[108.008,-17.794],[113.796,-12.007],[113.796,12.008],[108.008,17.795],[-108.01,17.795],[-113.796,12.008],[-113.796,-12.007],[-108.01,-17.794]],"c":true},"ix":2},"nm":"Path 2","mn":"ADBE Vector Shape - Group","hd":false},{"ty":"mm","mm":1,"nm":"Merge Paths 1","mn":"ADBE Vector Filter - Merge","hd":false},{"ty":"fl","c":{"a":0,"k":[0,0,0,1],"ix":4},"o":{"a":0,"k":100,"ix":5},"r":1,"bm":0,"nm":"Fill 1","mn":"ADBE Vector Graphic - Fill","hd":false},{"ty":"tr","p":{"a":0,"k":[115.503,19.503],"ix":2},"a":{"a":0,"k":[0,0],"ix":1},"s":{"a":0,"k":[100,100],"ix":3},"r":{"a":0,"k":0,"ix":6},"o":{"a":0,"k":100,"ix":7},"sk":{"a":0,"k":0,"ix":4},"sa":{"a":0,"k":0,"ix":5},"nm":"Transform"}],"nm":"Group 2","np":4,"cix":2,"bm":0,"ix":2,"mn":"ADBE Vector Group","hd":false},{"ty":"gr","it":[{"ind":0,"ty":"sh","ix":1,"ks":{"a":0,"k":{"i":[[0,0],[0,3.593],[0,0],[-3.593,0],[0,0],[0,-3.593],[0,0],[3.593,0]],"o":[[-3.593,0],[0,0],[0,-3.593],[0,0],[3.593,0],[0,0],[0,3.593],[0,0]],"v":[[-108.009,18.523],[-114.525,12.008],[-114.525,-12.007],[-108.009,-18.523],[108.009,-18.523],[114.525,-12.007],[114.525,12.008],[108.009,18.523]],"c":true},"ix":2},"nm":"Path 1","mn":"ADBE Vector Shape - Group","hd":false},{"ty":"fl","c":{"a":0,"k":[1,1,1,1],"ix":4},"o":{"a":0,"k":100,"ix":5},"r":1,"bm":0,"nm":"Fill 1","mn":"ADBE Vector Graphic - Fill","hd":false},{"ty":"tr","p":{"a":0,"k":[115.503,19.502],"ix":2},"a":{"a":0,"k":[0,0],"ix":1},"s":{"a":0,"k":[100,100],"ix":3},"r":{"a":0,"k":0,"ix":6},"o":{"a":0,"k":100,"ix":7},"sk":{"a":0,"k":0,"ix":4},"sa":{"a":0,"k":0,"ix":5},"nm":"Transform"}],"nm":"Group 3","np":2,"cix":2,"bm":0,"ix":3,"mn":"ADBE Vector Group","hd":false}],"ip":0,"op":503,"st":0,"bm":0},{"ddd":0,"ind":27,"ty":4,"nm":"la2-04 Outlines","parent":1,"sr":1,"ks":{"o":{"a":0,"k":100,"ix":11},"r":{"a":0,"k":0,"ix":10},"p":{"a":0,"k":[562.838,229.002,0],"ix":2},"a":{"a":0,"k":[115.503,19.503,0],"ix":1},"s":{"a":1,"k":[{"i":{"x":[0.833,0.833,0.833],"y":[0.833,0.833,0.833]},"o":{"x":[0.167,0.167,0.167],"y":[0.167,0.167,0.167]},"t":112,"s":[136.986,133.333,100]},{"i":{"x":[0.833,0.833,0.833],"y":[0.833,0.833,0.833]},"o":{"x":[0.167,0.167,0.167],"y":[0.167,0.167,0.167]},"t":115,"s":[145,141.133,100]},{"t":124,"s":[136.986,133.333,100]}],"ix":6}},"ao":0,"ef":[{"ty":20,"nm":"Tint","np":7,"mn":"ADBE Tint","ix":1,"en":1,"ef":[{"ty":2,"nm":"Map Black To","mn":"ADBE Tint-0001","ix":1,"v":{"a":0,"k":[0,0,0,0],"ix":1}},{"ty":2,"nm":"Map White To","mn":"ADBE Tint-0002","ix":2,"v":{"a":0,"k":[1,0.941176474094,0.250980407,1],"ix":2}},{"ty":0,"nm":"Amount to Tint","mn":"ADBE Tint-0003","ix":3,"v":{"a":1,"k":[{"i":{"x":[0.833],"y":[0.833]},"o":{"x":[0.167],"y":[0.167]},"t":112,"s":[0]},{"i":{"x":[0.833],"y":[0.833]},"o":{"x":[0.167],"y":[0.167]},"t":115,"s":[100]},{"t":124,"s":[0]}],"ix":3}},{"ty":6,"nm":"","mn":"ADBE Tint-0004","ix":4,"v":0},{"ty":7,"nm":"GPU Rendering","mn":"ADBE Force CPU GPU","ix":5,"v":{"a":0,"k":1,"ix":5}}]}],"shapes":[{"ty":"gr","it":[{"ind":0,"ty":"sh","ix":1,"ks":{"a":0,"k":{"i":[[0,0],[0,0],[0,0]],"o":[[0,0],[0,0],[0,0]],"v":[[-3.87,-8.351],[3.981,-0.5],[-3.982,8.351]],"c":false},"ix":2},"nm":"Path 1","mn":"ADBE Vector Shape - Group","hd":false},{"ty":"st","c":{"a":0,"k":[0,0,0,1],"ix":3},"o":{"a":0,"k":100,"ix":4},"w":{"a":0,"k":1.663,"ix":5},"lc":1,"lj":1,"ml":10,"bm":0,"nm":"Stroke 1","mn":"ADBE Vector Graphic - Stroke","hd":false},{"ty":"tr","p":{"a":0,"k":[213.974,18.799],"ix":2},"a":{"a":0,"k":[0,0],"ix":1},"s":{"a":0,"k":[100,100],"ix":3},"r":{"a":0,"k":0,"ix":6},"o":{"a":0,"k":100,"ix":7},"sk":{"a":0,"k":0,"ix":4},"sa":{"a":0,"k":0,"ix":5},"nm":"Transform"}],"nm":"Group 1","np":2,"cix":2,"bm":0,"ix":1,"mn":"ADBE Vector Group","hd":false},{"ty":"gr","it":[{"ind":0,"ty":"sh","ix":1,"ks":{"a":0,"k":{"i":[[4.001,0],[0,0],[0,-4.001],[0,0],[-4.001,0],[0,0],[0,4.001],[0,0]],"o":[[0,0],[-4.001,0],[0,0],[0,4.001],[0,0],[4.001,0],[0,0],[0,-4.001]],"v":[[108.008,-19.253],[-108.01,-19.253],[-115.253,-12.007],[-115.253,12.008],[-108.01,19.253],[108.008,19.253],[115.253,12.008],[115.253,-12.007]],"c":true},"ix":2},"nm":"Path 1","mn":"ADBE Vector Shape - Group","hd":false},{"ind":1,"ty":"sh","ix":2,"ks":{"a":0,"k":{"i":[[0,0],[0,-3.191],[0,0],[3.191,0],[0,0],[0,3.191],[0,0],[-3.19,0]],"o":[[3.191,0],[0,0],[0,3.191],[0,0],[-3.19,0],[0,0],[0,-3.191],[0,0]],"v":[[108.008,-17.794],[113.796,-12.007],[113.796,12.008],[108.008,17.795],[-108.01,17.795],[-113.796,12.008],[-113.796,-12.007],[-108.01,-17.794]],"c":true},"ix":2},"nm":"Path 2","mn":"ADBE Vector Shape - Group","hd":false},{"ty":"mm","mm":1,"nm":"Merge Paths 1","mn":"ADBE Vector Filter - Merge","hd":false},{"ty":"fl","c":{"a":0,"k":[0,0,0,1],"ix":4},"o":{"a":0,"k":100,"ix":5},"r":1,"bm":0,"nm":"Fill 1","mn":"ADBE Vector Graphic - Fill","hd":false},{"ty":"tr","p":{"a":0,"k":[115.503,19.503],"ix":2},"a":{"a":0,"k":[0,0],"ix":1},"s":{"a":0,"k":[100,100],"ix":3},"r":{"a":0,"k":0,"ix":6},"o":{"a":0,"k":100,"ix":7},"sk":{"a":0,"k":0,"ix":4},"sa":{"a":0,"k":0,"ix":5},"nm":"Transform"}],"nm":"Group 2","np":4,"cix":2,"bm":0,"ix":2,"mn":"ADBE Vector Group","hd":false},{"ty":"gr","it":[{"ind":0,"ty":"sh","ix":1,"ks":{"a":0,"k":{"i":[[0,0],[0,3.593],[0,0],[-3.593,0],[0,0],[0,-3.593],[0,0],[3.593,0]],"o":[[-3.593,0],[0,0],[0,-3.593],[0,0],[3.593,0],[0,0],[0,3.593],[0,0]],"v":[[-108.009,18.523],[-114.525,12.008],[-114.525,-12.007],[-108.009,-18.523],[108.009,-18.523],[114.525,-12.007],[114.525,12.008],[108.009,18.523]],"c":true},"ix":2},"nm":"Path 1","mn":"ADBE Vector Shape - Group","hd":false},{"ty":"fl","c":{"a":0,"k":[1,1,1,1],"ix":4},"o":{"a":0,"k":100,"ix":5},"r":1,"bm":0,"nm":"Fill 1","mn":"ADBE Vector Graphic - Fill","hd":false},{"ty":"tr","p":{"a":0,"k":[115.503,19.502],"ix":2},"a":{"a":0,"k":[0,0],"ix":1},"s":{"a":0,"k":[100,100],"ix":3},"r":{"a":0,"k":0,"ix":6},"o":{"a":0,"k":100,"ix":7},"sk":{"a":0,"k":0,"ix":4},"sa":{"a":0,"k":0,"ix":5},"nm":"Transform"}],"nm":"Group 3","np":2,"cix":2,"bm":0,"ix":3,"mn":"ADBE Vector Group","hd":false}],"ip":0,"op":503,"st":0,"bm":0},{"ddd":0,"ind":29,"ty":4,"nm":"la2-07 Outlines","parent":1,"sr":1,"ks":{"o":{"a":0,"k":100,"ix":11},"r":{"a":0,"k":0,"ix":10},"p":{"a":0,"k":[528.978,389.718,0],"ix":2},"a":{"a":0,"k":[90.786,5.906,0],"ix":1},"s":{"a":0,"k":[136.986,133.333,100],"ix":6}},"ao":0,"shapes":[{"ty":"gr","it":[{"ind":0,"ty":"sh","ix":1,"ks":{"a":0,"k":{"i":[[0,0],[0,0],[0,0],[0,0]],"o":[[0,0],[0,0],[0,0],[0,0]],"v":[[90.536,5.656],[-90.536,5.656],[-90.536,-5.656],[90.536,-5.656]],"c":true},"ix":2},"nm":"Path 1","mn":"ADBE Vector Shape - Group","hd":false},{"ty":"fl","c":{"a":0,"k":[0.8,0.8,0.8,1],"ix":4},"o":{"a":0,"k":100,"ix":5},"r":1,"bm":0,"nm":"Fill 1","mn":"ADBE Vector Graphic - Fill","hd":false},{"ty":"tr","p":{"a":0,"k":[90.786,5.906],"ix":2},"a":{"a":0,"k":[0,0],"ix":1},"s":{"a":0,"k":[100,100],"ix":3},"r":{"a":0,"k":0,"ix":6},"o":{"a":0,"k":100,"ix":7},"sk":{"a":0,"k":0,"ix":4},"sa":{"a":0,"k":0,"ix":5},"nm":"Transform"}],"nm":"Group 1","np":2,"cix":2,"bm":0,"ix":1,"mn":"ADBE Vector Group","hd":false}],"ip":0,"op":503,"st":0,"bm":0},{"ddd":0,"ind":31,"ty":4,"nm":"la2-05 Outlines","parent":1,"sr":1,"ks":{"o":{"a":0,"k":100,"ix":11},"r":{"a":0,"k":0,"ix":10},"p":{"a":0,"k":[528.978,284.385,0],"ix":2},"a":{"a":0,"k":[90.786,5.906,0],"ix":1},"s":{"a":0,"k":[136.986,133.333,100],"ix":6}},"ao":0,"shapes":[{"ty":"gr","it":[{"ind":0,"ty":"sh","ix":1,"ks":{"a":0,"k":{"i":[[0,0],[0,0],[0,0],[0,0]],"o":[[0,0],[0,0],[0,0],[0,0]],"v":[[90.536,5.656],[-90.536,5.656],[-90.536,-5.656],[90.536,-5.656]],"c":true},"ix":2},"nm":"Path 1","mn":"ADBE Vector Shape - Group","hd":false},{"ty":"fl","c":{"a":0,"k":[0.8,0.8,0.8,1],"ix":4},"o":{"a":0,"k":100,"ix":5},"r":1,"bm":0,"nm":"Fill 1","mn":"ADBE Vector Graphic - Fill","hd":false},{"ty":"tr","p":{"a":0,"k":[90.786,5.906],"ix":2},"a":{"a":0,"k":[0,0],"ix":1},"s":{"a":0,"k":[100,100],"ix":3},"r":{"a":0,"k":0,"ix":6},"o":{"a":0,"k":100,"ix":7},"sk":{"a":0,"k":0,"ix":4},"sa":{"a":0,"k":0,"ix":5},"nm":"Transform"}],"nm":"Group 1","np":2,"cix":2,"bm":0,"ix":1,"mn":"ADBE Vector Group","hd":false}],"ip":0,"op":503,"st":0,"bm":0},{"ddd":0,"ind":33,"ty":4,"nm":"la2-03 Outlines","parent":1,"sr":1,"ks":{"o":{"a":0,"k":100,"ix":11},"r":{"a":0,"k":0,"ix":10},"p":{"a":0,"k":[528.978,179.051,0],"ix":2},"a":{"a":0,"k":[90.786,5.906,0],"ix":1},"s":{"a":0,"k":[136.986,133.333,100],"ix":6}},"ao":0,"shapes":[{"ty":"gr","it":[{"ind":0,"ty":"sh","ix":1,"ks":{"a":0,"k":{"i":[[0,0],[0,0],[0,0],[0,0]],"o":[[0,0],[0,0],[0,0],[0,0]],"v":[[90.536,5.656],[-90.536,5.656],[-90.536,-5.656],[90.536,-5.656]],"c":true},"ix":2},"nm":"Path 1","mn":"ADBE Vector Shape - Group","hd":false},{"ty":"fl","c":{"a":0,"k":[0.8,0.8,0.8,1],"ix":4},"o":{"a":0,"k":100,"ix":5},"r":1,"bm":0,"nm":"Fill 1","mn":"ADBE Vector Graphic - Fill","hd":false},{"ty":"tr","p":{"a":0,"k":[90.786,5.906],"ix":2},"a":{"a":0,"k":[0,0],"ix":1},"s":{"a":0,"k":[100,100],"ix":3},"r":{"a":0,"k":0,"ix":6},"o":{"a":0,"k":100,"ix":7},"sk":{"a":0,"k":0,"ix":4},"sa":{"a":0,"k":0,"ix":5},"nm":"Transform"}],"nm":"Group 1","np":2,"cix":2,"bm":0,"ix":1,"mn":"ADBE Vector Group","hd":false}],"ip":0,"op":503,"st":0,"bm":0},{"ddd":0,"ind":35,"ty":4,"nm":"la2-02 Outlines","parent":1,"sr":1,"ks":{"o":{"a":0,"k":100,"ix":11},"r":{"a":0,"k":0,"ix":10},"p":{"a":0,"k":[440.139,536.409,0],"ix":2},"a":{"a":0,"k":[38.564,12.88,0],"ix":1},"s":{"a":0,"k":[136.986,133.333,100],"ix":6}},"ao":0,"shapes":[{"ty":"gr","it":[{"ind":0,"ty":"sh","ix":1,"ks":{"a":0,"k":{"i":[[0,0],[0,0]],"o":[[0,0],[0,0]],"v":[[12.88,12.88],[64.248,12.88]],"c":false},"ix":2},"nm":"Path 1","mn":"ADBE Vector Shape - Group","hd":false},{"ty":"st","c":{"a":0,"k":[0,0,0,1],"ix":3},"o":{"a":0,"k":100,"ix":4},"w":{"a":0,"k":5.152,"ix":5},"lc":1,"lj":1,"ml":10,"bm":0,"nm":"Stroke 1","mn":"ADBE Vector Graphic - Stroke","hd":false},{"ty":"tr","p":{"a":0,"k":[0,0],"ix":2},"a":{"a":0,"k":[0,0],"ix":1},"s":{"a":0,"k":[100,100],"ix":3},"r":{"a":0,"k":0,"ix":6},"o":{"a":0,"k":100,"ix":7},"sk":{"a":0,"k":0,"ix":4},"sa":{"a":0,"k":0,"ix":5},"nm":"Transform"}],"nm":"Group 1","np":2,"cix":2,"bm":0,"ix":1,"mn":"ADBE Vector Group","hd":false}],"ip":0,"op":503,"st":0,"bm":0},{"ddd":0,"ind":37,"ty":4,"nm":"la2-01 Outlines","parent":1,"sr":1,"ks":{"o":{"a":0,"k":100,"ix":11},"r":{"a":0,"k":0,"ix":10},"p":{"a":0,"k":[561.558,89.652,0],"ix":2},"a":{"a":0,"k":[142.85,45.701,0],"ix":1},"s":{"a":0,"k":[136.986,133.333,100],"ix":6}},"ao":0,"shapes":[{"ty":"gr","it":[{"ind":0,"ty":"sh","ix":1,"ks":{"a":0,"k":{"i":[[0,0],[0,0],[0,0],[0,0]],"o":[[0,0],[0,0],[0,0],[0,0]],"v":[[25.282,3.884],[-25.282,3.884],[-25.282,-3.884],[25.282,-3.884]],"c":true},"ix":2},"nm":"Path 1","mn":"ADBE Vector Shape - Group","hd":false},{"ty":"fl","c":{"a":0,"k":[0.8,0.8,0.8,1],"ix":4},"o":{"a":0,"k":100,"ix":5},"r":1,"bm":0,"nm":"Fill 1","mn":"ADBE Vector Graphic - Fill","hd":false},{"ty":"tr","p":{"a":0,"k":[99.388,31.313],"ix":2},"a":{"a":0,"k":[0,0],"ix":1},"s":{"a":0,"k":[100,100],"ix":3},"r":{"a":0,"k":0,"ix":6},"o":{"a":0,"k":100,"ix":7},"sk":{"a":0,"k":0,"ix":4},"sa":{"a":0,"k":0,"ix":5},"nm":"Transform"}],"nm":"Group 1","np":2,"cix":2,"bm":0,"ix":1,"mn":"ADBE Vector Group","hd":false},{"ty":"gr","it":[{"ind":0,"ty":"sh","ix":1,"ks":{"a":0,"k":{"i":[[0,0],[0,0],[0,0],[0,0]],"o":[[0,0],[0,0],[0,0],[0,0]],"v":[[40.501,3.884],[-40.502,3.884],[-40.502,-3.884],[40.501,-3.884]],"c":true},"ix":2},"nm":"Path 1","mn":"ADBE Vector Shape - Group","hd":false},{"ty":"fl","c":{"a":0,"k":[0.8,0.8,0.8,1],"ix":4},"o":{"a":0,"k":100,"ix":5},"r":1,"bm":0,"nm":"Fill 1","mn":"ADBE Vector Graphic - Fill","hd":false},{"ty":"tr","p":{"a":0,"k":[114.607,16.11],"ix":2},"a":{"a":0,"k":[0,0],"ix":1},"s":{"a":0,"k":[100,100],"ix":3},"r":{"a":0,"k":0,"ix":6},"o":{"a":0,"k":100,"ix":7},"sk":{"a":0,"k":0,"ix":4},"sa":{"a":0,"k":0,"ix":5},"nm":"Transform"}],"nm":"Group 2","np":2,"cix":2,"bm":0,"ix":2,"mn":"ADBE Vector Group","hd":false},{"ty":"gr","it":[{"ind":0,"ty":"sh","ix":1,"ks":{"a":0,"k":{"i":[[0,0],[0,0],[0,0],[0,0]],"o":[[0,0],[0,0],[0,0],[0,0]],"v":[[1.109,7.134],[-1.046,7.134],[-1.046,4.966],[1.109,4.966]],"c":true},"ix":2},"nm":"Path 1","mn":"ADBE Vector Shape - Group","hd":false},{"ind":1,"ty":"sh","ix":2,"ks":{"a":0,"k":{"i":[[0,0]],"o":[[0,0]],"v":[[1.109,4.965]],"c":false},"ix":2},"nm":"Path 2","mn":"ADBE Vector Shape - Group","hd":false},{"ind":2,"ty":"sh","ix":3,"ks":{"a":0,"k":{"i":[[-0.202,0.596],[-0.384,0.436],[-0.525,0.224],[-0.626,-0.007],[-0.535,-0.179],[-0.375,-0.336],[-0.189,-0.465],[0.011,-0.568],[0.103,-0.352],[0.162,-0.272],[0.202,-0.22],[0,0],[0,0],[0.165,-0.23],[0.095,-0.263],[-0.004,-0.308],[0,0],[0,0],[0,0],[-0.186,0.435],[-0.261,0.312],[-0.283,0.257],[-0.244,0.282],[-0.144,0.334],[0.034,0.416],[0.429,0.454],[0.613,-0.032],[0.379,-0.173],[0.229,-0.288],[0.093,-0.369],[-0.005,-0.425],[0,0]],"o":[[0.187,-0.551],[0.379,-0.427],[0.577,-0.243],[0.564,-0.008],[0.476,0.162],[0.371,0.34],[0.211,0.528],[0.004,0.367],[-0.093,0.303],[-0.155,0.254],[0,0],[0,0],[-0.2,0.2],[-0.161,0.228],[-0.103,0.29],[0,0],[0,0],[0,0],[0.014,-0.473],[0.167,-0.371],[0.247,-0.291],[0.277,-0.249],[0.239,-0.274],[0.151,-0.389],[-0.013,-0.624],[-0.449,-0.418],[-0.416,-0.01],[-0.33,0.164],[-0.234,0.301],[-0.105,0.412],[0,0],[-0.021,-0.628]],"v":[[-3.941,-4.285],[-3.076,-5.781],[-1.703,-6.769],[0.122,-7.126],[1.783,-6.866],[3.073,-6.111],[3.923,-4.889],[4.226,-3.228],[4.075,-2.144],[3.691,-1.279],[3.155,-0.566],[2.538,0.079],[1.92,0.669],[1.37,1.315],[0.986,2.056],[0.836,2.961],[0.836,3.716],[-0.77,3.716],[-0.77,2.797],[-0.468,1.424],[0.176,0.395],[0.973,-0.429],[1.755,-1.225],[2.331,-2.144],[2.51,-3.366],[1.824,-5.04],[0.163,-5.644],[-1.046,-5.397],[-1.895,-4.711],[-2.391,-3.695],[-2.541,-2.433],[-4.215,-2.433]],"c":true},"ix":2},"nm":"Path 3","mn":"ADBE Vector Shape - Group","hd":false},{"ty":"mm","mm":1,"nm":"Merge Paths 1","mn":"ADBE Vector Filter - Merge","hd":false},{"ty":"fl","c":{"a":0,"k":[0,0,0,1],"ix":4},"o":{"a":0,"k":100,"ix":5},"r":1,"bm":0,"nm":"Fill 1","mn":"ADBE Vector Graphic - Fill","hd":false},{"ty":"tr","p":{"a":0,"k":[242.511,20.689],"ix":2},"a":{"a":0,"k":[0,0],"ix":1},"s":{"a":0,"k":[100,100],"ix":3},"r":{"a":0,"k":0,"ix":6},"o":{"a":0,"k":100,"ix":7},"sk":{"a":0,"k":0,"ix":4},"sa":{"a":0,"k":0,"ix":5},"nm":"Transform"}],"nm":"Group 3","np":5,"cix":2,"bm":0,"ix":3,"mn":"ADBE Vector Group","hd":false},{"ty":"gr","it":[{"ind":0,"ty":"sh","ix":1,"ks":{"a":0,"k":{"i":[[0,0],[0.061,-8.338],[-8.338,-0.061],[-0.06,8.337],[0.001,0.073],[8.295,0.06]],"o":[[-8.338,-0.06],[-0.06,8.337],[8.338,0.06],[0.001,-0.074],[0,-8.296],[0,0]],"v":[[0.14,-14.988],[-15.067,0],[-0.079,15.206],[15.127,0.219],[15.127,0],[0.14,-15.097]],"c":true},"ix":2},"nm":"Path 1","mn":"ADBE Vector Shape - Group","hd":false},{"ind":1,"ty":"sh","ix":2,"ks":{"a":0,"k":{"i":[[9.053,-0.061],[0.06,9.095],[-9.095,0.06],[-0.06,-9.096],[0,-0.037]],"o":[[-9.096,0.06],[-0.061,-9.096],[9.096,-0.061],[0,0.037],[0,9.053]],"v":[[0.14,16.47],[-16.439,0.11],[-0.08,-16.469],[16.499,-0.11],[16.5,0]],"c":true},"ix":2},"nm":"Path 2","mn":"ADBE Vector Shape - Group","hd":false},{"ty":"mm","mm":1,"nm":"Merge Paths 1","mn":"ADBE Vector Filter - Merge","hd":false},{"ty":"fl","c":{"a":0,"k":[0,0,0,1],"ix":4},"o":{"a":0,"k":100,"ix":5},"r":1,"bm":0,"nm":"Fill 1","mn":"ADBE Vector Graphic - Fill","hd":false},{"ty":"tr","p":{"a":0,"k":[242.383,20.7],"ix":2},"a":{"a":0,"k":[0,0],"ix":1},"s":{"a":0,"k":[100,100],"ix":3},"r":{"a":0,"k":0,"ix":6},"o":{"a":0,"k":100,"ix":7},"sk":{"a":0,"k":0,"ix":4},"sa":{"a":0,"k":0,"ix":5},"nm":"Transform"}],"nm":"Group 4","np":4,"cix":2,"bm":0,"ix":4,"mn":"ADBE Vector Group","hd":false},{"ty":"gr","it":[{"ind":0,"ty":"sh","ix":1,"ks":{"a":0,"k":{"i":[[-1.408,-0.001],[-0.598,-0.248],[0.06,-2.114],[0,0],[0,0],[-1.285,0.136],[0,0],[0,0],[-1.928,0.81],[-0.633,-0.003],[-1.007,-0.997],[0,0],[0,0],[-0.828,1.015],[0,0],[0,0],[-1.904,2.065],[-1.431,-0.009],[0,0],[0,0],[0.137,1.285],[0,0],[0,0],[0.065,0.005],[0.048,2.807],[-1.02,0.98],[0,0],[0,0],[1.002,0.818],[0,0],[0,0],[1.408,0.002],[0.599,0.247],[-0.06,2.114],[0,0],[0,0],[0.663,0.001],[0.627,-0.065],[0,0],[0,0],[1.929,-0.811],[0.631,0.002],[1.007,0.994],[0,0],[0,0],[0.826,-1.015],[0,0],[0,0],[0.795,-1.966],[2.107,0.032],[0,0],[0,0],[-0.136,-1.285],[0,0],[0,0],[-0.07,-0.007],[0,0],[-0.773,-1.884],[1.525,-1.453],[0,0],[0,0],[-1.002,-0.818],[0,0],[0,0]],"o":[[0.647,-0.004],[1.943,0.834],[0,0],[0,0],[1.285,0.136],[0,0],[0,0],[-0.017,-2.09],[0.588,-0.238],[1.417,-0.015],[0,0],[0,0],[1.027,-0.813],[0,0],[0,0],[-2.064,-1.904],[0.971,-1.052],[0,0],[0,0],[0.137,-1.286],[0,0],[0,0],[-0.058,-0.03],[-2.808,0.048],[-0.024,-1.415],[0,0],[0,0],[-0.805,-1.012],[0,0],[0,0],[-0.992,0.999],[-0.647,0.004],[-1.943,-0.835],[0,0],[0,0],[-0.659,-0.073],[-0.63,0],[0,0],[0,0],[0.02,2.093],[-0.586,0.237],[-1.415,0.016],[0,0],[0,0],[-1.025,0.814],[0,0],[0,0],[1.553,1.446],[-0.866,1.921],[0,0],[0,0],[-0.136,1.286],[0,0],[0,0],[0.063,0.031],[0,0],[2.037,0.03],[0.782,1.956],[0,0],[0,0],[0.806,1.012],[0,0],[0,0],[0.992,-1]],"v":[[-7.298,12.591],[-5.41,12.959],[-2.291,17.843],[-2.291,18.139],[-1.995,18.173],[1.871,18.173],[2.161,18.173],[2.161,17.876],[5.319,13.081],[7.168,12.726],[10.957,14.26],[11.157,14.473],[11.389,14.292],[14.179,11.541],[14.366,11.309],[14.147,11.104],[13.856,3.919],[17.627,2.281],[18.103,2.281],[18.136,1.985],[18.136,-1.882],[18.136,-2.062],[17.974,-2.139],[17.788,-2.191],[12.617,-7.187],[14.179,-10.942],[14.392,-11.148],[14.205,-11.38],[11.486,-14.132],[11.254,-14.318],[11.048,-14.098],[7.297,-12.54],[5.409,-12.907],[2.29,-17.792],[2.29,-18.088],[1.994,-18.12],[0.009,-18.23],[-1.879,-18.133],[-2.169,-18.133],[-2.169,-17.837],[-5.326,-13.036],[-7.169,-12.68],[-10.952,-14.209],[-11.158,-14.422],[-11.39,-14.241],[-14.174,-11.49],[-14.36,-11.258],[-14.142,-11.051],[-12.885,-5.387],[-17.782,-2.275],[-18.066,-2.275],[-18.066,-1.992],[-18.066,1.876],[-18.066,2.055],[-17.905,2.133],[-17.705,2.191],[-17.576,2.191],[-12.943,5.348],[-14.174,10.993],[-14.386,11.199],[-14.206,11.432],[-11.486,14.183],[-11.255,14.37],[-11.048,14.152]],"c":true},"ix":2},"nm":"Path 1","mn":"ADBE Vector Shape - Group","hd":false},{"ind":1,"ty":"sh","ix":2,"ks":{"a":0,"k":{"i":[[0.719,0.002],[0.764,0.09],[-0.058,1.019],[1.329,0.547],[0.415,-0.004],[0.674,-0.701],[0.796,0.64],[0.927,1.191],[-0.743,0.683],[0.527,1.307],[1.335,0.026],[0,0],[0.198,1.013],[-0.17,1.499],[-0.992,-0.026],[-0.617,1.307],[1.058,0.955],[-0.636,0.796],[-1.194,0.947],[-0.681,-0.745],[-0.971,0.006],[-0.376,0.15],[0.042,1.399],[-1.004,0.11],[-1.499,-0.171],[0.057,-1.021],[-1.315,-0.566],[-0.416,0.004],[-0.676,0.699],[-0.798,-0.635],[-0.928,-1.192],[0.743,-0.683],[-1.239,-1.374],[-0.968,0.016],[-0.184,-1.005],[0.17,-1.499],[0.986,0.007],[0,0],[0.535,-1.238],[-1.057,-0.955],[0.641,-0.797],[1.193,-0.947],[0.433,0],[0.361,0.404],[0.971,-0.003],[0.376,-0.149],[-0.043,-1.4],[1.004,-0.111]],"o":[[-0.769,-0.001],[-1.014,-0.121],[0.084,-1.435],[-0.385,-0.157],[-0.972,-0.005],[-0.688,0.756],[-1.172,-0.951],[-0.623,-0.794],[1.038,-0.952],[-0.502,-1.237],[0,0],[-1.032,0.029],[-0.17,-1.499],[0.097,-0.988],[1.444,0.065],[0.548,-1.316],[-0.752,-0.687],[0.947,-1.193],[0.796,-0.621],[0.677,0.697],[0.406,0.005],[1.292,-0.541],[-0.034,-1.01],[1.499,-0.171],[1.017,0.117],[-0.101,1.43],[0.385,0.157],[0.971,0.007],[0.685,-0.754],[1.174,0.95],[0.622,0.794],[-1.374,1.24],[0.648,0.719],[1.021,-0.016],[0.17,1.499],[-0.116,0.978],[0,0],[-1.349,0.012],[-0.548,1.316],[0.757,0.688],[-0.947,1.194],[-0.341,0.267],[-0.542,-0.006],[-0.677,-0.696],[-0.406,-0.004],[-1.294,0.54],[0.034,1.01],[-0.715,0.075]],"v":[[0.003,20.002],[-2.298,19.867],[-3.999,17.837],[-6.08,14.524],[-7.292,14.292],[-9.869,15.382],[-12.511,15.588],[-15.669,12.365],[-15.456,9.749],[-14.606,5.993],[-17.634,3.911],[-17.712,3.911],[-19.844,2.204],[-19.844,-2.307],[-17.911,-4.014],[-14.509,-6.064],[-15.36,-9.853],[-15.566,-12.489],[-12.344,-15.71],[-9.728,-15.491],[-7.15,-14.409],[-5.965,-14.628],[-3.889,-17.848],[-2.169,-19.834],[2.342,-19.834],[4.05,-17.805],[6.079,-14.473],[7.291,-14.241],[9.869,-15.324],[12.504,-15.536],[15.668,-12.314],[15.455,-9.697],[15.212,-4.965],[17.756,-3.86],[19.844,-2.146],[19.844,2.365],[17.91,4.072],[17.588,4.072],[14.489,6.128],[15.339,9.917],[15.545,12.559],[12.324,15.781],[11.131,16.193],[9.714,15.549],[7.136,14.466],[5.951,14.686],[3.875,17.907],[2.155,19.893]],"c":true},"ix":2},"nm":"Path 2","mn":"ADBE Vector Shape - Group","hd":false},{"ty":"mm","mm":1,"nm":"Merge Paths 1","mn":"ADBE Vector Filter - Merge","hd":false},{"ty":"fl","c":{"a":0,"k":[0,0,0,1],"ix":4},"o":{"a":0,"k":100,"ix":5},"r":1,"bm":0,"nm":"Fill 1","mn":"ADBE Vector Graphic - Fill","hd":false},{"ty":"tr","p":{"a":0,"k":[41.69,20.255],"ix":2},"a":{"a":0,"k":[0,0],"ix":1},"s":{"a":0,"k":[100,100],"ix":3},"r":{"a":0,"k":0,"ix":6},"o":{"a":0,"k":100,"ix":7},"sk":{"a":0,"k":0,"ix":4},"sa":{"a":0,"k":0,"ix":5},"nm":"Transform"}],"nm":"Group 5","np":4,"cix":2,"bm":0,"ix":5,"mn":"ADBE Vector Group","hd":false},{"ty":"gr","it":[{"ind":0,"ty":"sh","ix":1,"ks":{"a":0,"k":{"i":[[3.511,-0.004],[0,3.512],[-3.513,0],[0,-3.513]],"o":[[-3.513,0],[0,-3.513],[3.513,0],[-0.004,3.511]],"v":[[0,6.36],[-6.36,0.001],[0,-6.359],[6.36,0.001]],"c":true},"ix":2},"nm":"Path 1","mn":"ADBE Vector Shape - Group","hd":false},{"ind":1,"ty":"sh","ix":2,"ks":{"a":0,"k":{"i":[[4.447,0.003],[0,-4.449],[-4.449,0],[0,4.448]],"o":[[-4.449,0],[0,4.448],[4.449,0],[-0.004,-4.448]],"v":[[0,-8.054],[-8.055,0.001],[0,8.054],[8.055,0.001]],"c":true},"ix":2},"nm":"Path 2","mn":"ADBE Vector Shape - Group","hd":false},{"ty":"mm","mm":1,"nm":"Merge Paths 1","mn":"ADBE Vector Filter - Merge","hd":false},{"ty":"fl","c":{"a":0,"k":[0,0,0,1],"ix":4},"o":{"a":0,"k":100,"ix":5},"r":1,"bm":0,"nm":"Fill 1","mn":"ADBE Vector Graphic - Fill","hd":false},{"ty":"tr","p":{"a":0,"k":[41.693,20.28],"ix":2},"a":{"a":0,"k":[0,0],"ix":1},"s":{"a":0,"k":[100,100],"ix":3},"r":{"a":0,"k":0,"ix":6},"o":{"a":0,"k":100,"ix":7},"sk":{"a":0,"k":0,"ix":4},"sa":{"a":0,"k":0,"ix":5},"nm":"Transform"}],"nm":"Group 6","np":4,"cix":2,"bm":0,"ix":6,"mn":"ADBE Vector Group","hd":false},{"ty":"gr","it":[{"ind":0,"ty":"sh","ix":1,"ks":{"a":0,"k":{"i":[[0,0],[0,0]],"o":[[0,0],[0,0]],"v":[[7.287,84.114],[278.412,84.114]],"c":false},"ix":2},"nm":"Path 1","mn":"ADBE Vector Shape - Group","hd":false},{"ty":"st","c":{"a":0,"k":[1,0.941000007181,0.250999989229,1],"ix":3},"o":{"a":0,"k":100,"ix":4},"w":{"a":0,"k":2.915,"ix":5},"lc":1,"lj":1,"ml":10,"bm":0,"nm":"Stroke 1","mn":"ADBE Vector Graphic - Stroke","hd":false},{"ty":"tr","p":{"a":0,"k":[0,0],"ix":2},"a":{"a":0,"k":[0,0],"ix":1},"s":{"a":0,"k":[100,100],"ix":3},"r":{"a":0,"k":0,"ix":6},"o":{"a":0,"k":100,"ix":7},"sk":{"a":0,"k":0,"ix":4},"sa":{"a":0,"k":0,"ix":5},"nm":"Transform"}],"nm":"Group 7","np":2,"cix":2,"bm":0,"ix":7,"mn":"ADBE Vector Group","hd":false}],"ip":0,"op":503,"st":0,"bm":0},{"ddd":0,"ind":39,"ty":4,"nm":"la1-12 Outlines","parent":1,"sr":1,"ks":{"o":{"a":0,"k":100,"ix":11},"r":{"a":0,"k":0,"ix":10},"p":{"a":0,"k":[337.455,315.282,0],"ix":2},"a":{"a":0,"k":[10.332,17.11,0],"ix":1},"s":{"a":0,"k":[136.986,133.333,100],"ix":6}},"ao":0,"shapes":[{"ty":"gr","it":[{"ind":0,"ty":"sh","ix":1,"ks":{"a":0,"k":{"i":[[0,0],[0,0],[0,0]],"o":[[0,0],[0,0],[0,0]],"v":[[-6.003,-12.953],[6.175,-0.775],[-6.175,12.953]],"c":false},"ix":2},"nm":"Path 1","mn":"ADBE Vector Shape - Group","hd":false},{"ty":"st","c":{"a":0,"k":[0,0,0,1],"ix":3},"o":{"a":0,"k":100,"ix":4},"w":{"a":0,"k":1.663,"ix":5},"lc":1,"lj":1,"ml":10,"bm":0,"nm":"Stroke 1","mn":"ADBE Vector Graphic - Stroke","hd":false},{"ty":"tr","p":{"a":0,"k":[10.332,17.11],"ix":2},"a":{"a":0,"k":[0,0],"ix":1},"s":{"a":0,"k":[100,100],"ix":3},"r":{"a":0,"k":0,"ix":6},"o":{"a":0,"k":100,"ix":7},"sk":{"a":0,"k":0,"ix":4},"sa":{"a":0,"k":0,"ix":5},"nm":"Transform"}],"nm":"Group 1","np":2,"cix":2,"bm":0,"ix":1,"mn":"ADBE Vector Group","hd":false}],"ip":0,"op":503,"st":0,"bm":0},{"ddd":0,"ind":41,"ty":4,"nm":"la1-09 Outlines","parent":1,"sr":1,"ks":{"o":{"a":0,"k":100,"ix":11},"r":{"a":0,"k":0,"ix":10},"p":{"a":0,"k":[337.455,248.615,0],"ix":2},"a":{"a":0,"k":[10.332,17.11,0],"ix":1},"s":{"a":0,"k":[136.986,133.333,100],"ix":6}},"ao":0,"shapes":[{"ty":"gr","it":[{"ind":0,"ty":"sh","ix":1,"ks":{"a":0,"k":{"i":[[0,0],[0,0],[0,0]],"o":[[0,0],[0,0],[0,0]],"v":[[-6.003,-12.953],[6.175,-0.775],[-6.175,12.953]],"c":false},"ix":2},"nm":"Path 1","mn":"ADBE Vector Shape - Group","hd":false},{"ty":"st","c":{"a":0,"k":[0,0,0,1],"ix":3},"o":{"a":0,"k":100,"ix":4},"w":{"a":0,"k":1.663,"ix":5},"lc":1,"lj":1,"ml":10,"bm":0,"nm":"Stroke 1","mn":"ADBE Vector Graphic - Stroke","hd":false},{"ty":"tr","p":{"a":0,"k":[10.332,17.11],"ix":2},"a":{"a":0,"k":[0,0],"ix":1},"s":{"a":0,"k":[100,100],"ix":3},"r":{"a":0,"k":0,"ix":6},"o":{"a":0,"k":100,"ix":7},"sk":{"a":0,"k":0,"ix":4},"sa":{"a":0,"k":0,"ix":5},"nm":"Transform"}],"nm":"Group 1","np":2,"cix":2,"bm":0,"ix":1,"mn":"ADBE Vector Group","hd":false}],"ip":0,"op":503,"st":0,"bm":0},{"ddd":0,"ind":43,"ty":4,"nm":"la1-06 Outlines","parent":1,"sr":1,"ks":{"o":{"a":0,"k":100,"ix":11},"r":{"a":0,"k":0,"ix":10},"p":{"a":0,"k":[337.455,181.948,0],"ix":2},"a":{"a":0,"k":[10.332,17.11,0],"ix":1},"s":{"a":0,"k":[136.986,133.333,100],"ix":6}},"ao":0,"shapes":[{"ty":"gr","it":[{"ind":0,"ty":"sh","ix":1,"ks":{"a":0,"k":{"i":[[0,0],[0,0],[0,0]],"o":[[0,0],[0,0],[0,0]],"v":[[-6.003,-12.953],[6.175,-0.775],[-6.175,12.953]],"c":false},"ix":2},"nm":"Path 1","mn":"ADBE Vector Shape - Group","hd":false},{"ty":"st","c":{"a":0,"k":[0,0,0,1],"ix":3},"o":{"a":0,"k":100,"ix":4},"w":{"a":0,"k":1.663,"ix":5},"lc":1,"lj":1,"ml":10,"bm":0,"nm":"Stroke 1","mn":"ADBE Vector Graphic - Stroke","hd":false},{"ty":"tr","p":{"a":0,"k":[10.332,17.11],"ix":2},"a":{"a":0,"k":[0,0],"ix":1},"s":{"a":0,"k":[100,100],"ix":3},"r":{"a":0,"k":0,"ix":6},"o":{"a":0,"k":100,"ix":7},"sk":{"a":0,"k":0,"ix":4},"sa":{"a":0,"k":0,"ix":5},"nm":"Transform"}],"nm":"Group 1","np":2,"cix":2,"bm":0,"ix":1,"mn":"ADBE Vector Group","hd":false}],"ip":0,"op":503,"st":0,"bm":0},{"ddd":0,"ind":45,"ty":4,"nm":"la1-11 Outlines","parent":1,"sr":1,"ks":{"o":{"a":0,"k":100,"ix":11},"r":{"a":0,"k":0,"ix":10},"p":{"a":0,"k":[86.644,316.009,0],"ix":2},"a":{"a":0,"k":[0,12,0],"ix":1},"s":{"a":1,"k":[{"i":{"x":[0.833,0.833,0.833],"y":[0.833,0.833,0.833]},"o":{"x":[0.167,0.167,0.167],"y":[0.167,0.167,0.167]},"t":10,"s":[128.261,133.333,100]},{"i":{"x":[0.833,0.833,0.833],"y":[0.833,0.833,0.833]},"o":{"x":[0.167,0.167,0.167],"y":[0.167,0.167,0.167]},"t":15,"s":[136.114,133.333,100]},{"i":{"x":[0.833,0.833,0.833],"y":[0.833,0.833,0.833]},"o":{"x":[0.167,0.167,0.167],"y":[0.167,0.167,0.167]},"t":37,"s":[136.114,133.333,100]},{"t":42,"s":[128.261,133.333,100]}],"ix":6}},"ao":0,"shapes":[{"ty":"gr","it":[{"ind":0,"ty":"sh","ix":1,"ks":{"a":0,"k":{"i":[[0,0],[0,0],[0,0],[0,0]],"o":[[0,0],[0,0],[0,0],[0,0]],"v":[[78.025,11.356],[-78.025,11.356],[-78.025,-11.356],[78.025,-11.356]],"c":true},"ix":2},"nm":"Path 1","mn":"ADBE Vector Shape - Group","hd":false},{"ty":"fl","c":{"a":0,"k":[0.8,0.8,0.8,1],"ix":4},"o":{"a":0,"k":100,"ix":5},"r":1,"bm":0,"nm":"Fill 1","mn":"ADBE Vector Graphic - Fill","hd":false},{"ty":"tr","p":{"a":0,"k":[78.274,11.606],"ix":2},"a":{"a":0,"k":[0,0],"ix":1},"s":{"a":0,"k":[100,100],"ix":3},"r":{"a":0,"k":0,"ix":6},"o":{"a":0,"k":100,"ix":7},"sk":{"a":0,"k":0,"ix":4},"sa":{"a":0,"k":0,"ix":5},"nm":"Transform"}],"nm":"Group 1","np":2,"cix":2,"bm":0,"ix":1,"mn":"ADBE Vector Group","hd":false}],"ip":0,"op":503,"st":0,"bm":0},{"ddd":0,"ind":47,"ty":4,"nm":"la1-08 Outlines","parent":1,"sr":1,"ks":{"o":{"a":0,"k":100,"ix":11},"r":{"a":0,"k":0,"ix":10},"p":{"a":0,"k":[86.644,249.343,0],"ix":2},"a":{"a":0,"k":[0,12,0],"ix":1},"s":{"a":1,"k":[{"i":{"x":[0.833,0.833,0.833],"y":[0.833,0.833,0.833]},"o":{"x":[0.167,0.167,0.167],"y":[0.167,0.167,0.167]},"t":5,"s":[128.261,133.333,100]},{"i":{"x":[0.833,0.833,0.833],"y":[0.833,0.833,0.833]},"o":{"x":[0.167,0.167,0.167],"y":[0.167,0.167,0.167]},"t":10,"s":[136.986,133.333,100]},{"i":{"x":[0.833,0.833,0.833],"y":[0.833,0.833,0.833]},"o":{"x":[0.167,0.167,0.167],"y":[0.167,0.167,0.167]},"t":15,"s":[128.261,133.333,100]},{"i":{"x":[0.833,0.833,0.833],"y":[0.833,0.833,0.833]},"o":{"x":[0.167,0.167,0.167],"y":[0.167,0.167,0.167]},"t":37,"s":[128.261,133.333,100]},{"i":{"x":[0.833,0.833,0.833],"y":[0.833,0.833,0.833]},"o":{"x":[0.167,0.167,0.167],"y":[0.167,0.167,0.167]},"t":42,"s":[136.986,133.333,100]},{"i":{"x":[0.833,0.833,0.833],"y":[0.833,0.833,0.833]},"o":{"x":[0.167,0.167,0.167],"y":[0.167,0.167,0.167]},"t":64,"s":[136.986,133.333,100]},{"i":{"x":[0.833,0.833,0.833],"y":[0.833,0.833,0.833]},"o":{"x":[0.167,0.167,0.167],"y":[0.167,0.167,0.167]},"t":68,"s":[150,146,100]},{"i":{"x":[0.833,0.833,0.833],"y":[0.833,0.833,0.833]},"o":{"x":[0.167,0.167,0.167],"y":[0.167,0.167,0.167]},"t":77,"s":[136.986,133.333,100]},{"i":{"x":[0.833,0.833,0.833],"y":[0.833,0.833,0.833]},"o":{"x":[0.167,0.167,0.167],"y":[0.167,0.167,0.167]},"t":83,"s":[136.986,133.333,100]},{"t":87,"s":[128.261,133.333,100]}],"ix":6}},"ao":0,"ef":[{"ty":20,"nm":"Tint","np":7,"mn":"ADBE Tint","ix":1,"en":1,"ef":[{"ty":2,"nm":"Map Black To","mn":"ADBE Tint-0001","ix":1,"v":{"a":0,"k":[1,0.941176474094,0.250980407,1],"ix":1}},{"ty":2,"nm":"Map White To","mn":"ADBE Tint-0002","ix":2,"v":{"a":0,"k":[1,0.941176474094,0.250980407,1],"ix":2}},{"ty":0,"nm":"Amount to Tint","mn":"ADBE Tint-0003","ix":3,"v":{"a":1,"k":[{"i":{"x":[0.833],"y":[0.833]},"o":{"x":[0.167],"y":[0.167]},"t":64,"s":[0]},{"i":{"x":[0.833],"y":[0.833]},"o":{"x":[0.167],"y":[0.167]},"t":68,"s":[100]},{"t":77,"s":[0]}],"ix":3}},{"ty":6,"nm":"","mn":"ADBE Tint-0004","ix":4,"v":0},{"ty":7,"nm":"GPU Rendering","mn":"ADBE Force CPU GPU","ix":5,"v":{"a":0,"k":1,"ix":5}}]}],"shapes":[{"ty":"gr","it":[{"ind":0,"ty":"sh","ix":1,"ks":{"a":0,"k":{"i":[[0,0],[0,0],[0,0],[0,0]],"o":[[0,0],[0,0],[0,0],[0,0]],"v":[[78.025,11.356],[-78.025,11.356],[-78.025,-11.356],[78.025,-11.356]],"c":true},"ix":2},"nm":"Path 1","mn":"ADBE Vector Shape - Group","hd":false},{"ty":"fl","c":{"a":0,"k":[0.8,0.8,0.8,1],"ix":4},"o":{"a":0,"k":100,"ix":5},"r":1,"bm":0,"nm":"Fill 1","mn":"ADBE Vector Graphic - Fill","hd":false},{"ty":"tr","p":{"a":0,"k":[78.274,11.606],"ix":2},"a":{"a":0,"k":[0,0],"ix":1},"s":{"a":0,"k":[100,100],"ix":3},"r":{"a":0,"k":0,"ix":6},"o":{"a":0,"k":100,"ix":7},"sk":{"a":0,"k":0,"ix":4},"sa":{"a":0,"k":0,"ix":5},"nm":"Transform"}],"nm":"Group 1","np":2,"cix":2,"bm":0,"ix":1,"mn":"ADBE Vector Group","hd":false}],"ip":0,"op":503,"st":0,"bm":0},{"ddd":0,"ind":49,"ty":4,"nm":"la1-05 Outlines","parent":1,"sr":1,"ks":{"o":{"a":0,"k":100,"ix":11},"r":{"a":0,"k":0,"ix":10},"p":{"a":0,"k":[86.644,182.676,0],"ix":2},"a":{"a":0,"k":[0,12,0],"ix":1},"s":{"a":1,"k":[{"i":{"x":[0.833,0.833,0.833],"y":[0.833,0.833,0.833]},"o":{"x":[0.167,0.167,0.167],"y":[0.167,0.167,0.167]},"t":0,"s":[128.261,133.333,100]},{"i":{"x":[0.833,0.833,0.833],"y":[0.833,0.833,0.833]},"o":{"x":[0.167,0.167,0.167],"y":[0.167,0.167,0.167]},"t":5,"s":[136.986,133.333,100]},{"t":10,"s":[128.261,133.333,100]}],"ix":6}},"ao":0,"shapes":[{"ty":"gr","it":[{"ind":0,"ty":"sh","ix":1,"ks":{"a":0,"k":{"i":[[0,0],[0,0],[0,0],[0,0]],"o":[[0,0],[0,0],[0,0],[0,0]],"v":[[78.025,11.356],[-78.025,11.356],[-78.025,-11.356],[78.025,-11.356]],"c":true},"ix":2},"nm":"Path 1","mn":"ADBE Vector Shape - Group","hd":false},{"ty":"fl","c":{"a":0,"k":[0.8,0.8,0.8,1],"ix":4},"o":{"a":0,"k":100,"ix":5},"r":1,"bm":0,"nm":"Fill 1","mn":"ADBE Vector Graphic - Fill","hd":false},{"ty":"tr","p":{"a":0,"k":[78.274,11.606],"ix":2},"a":{"a":0,"k":[0,0],"ix":1},"s":{"a":0,"k":[100,100],"ix":3},"r":{"a":0,"k":0,"ix":6},"o":{"a":0,"k":100,"ix":7},"sk":{"a":0,"k":0,"ix":4},"sa":{"a":0,"k":0,"ix":5},"nm":"Transform"}],"nm":"Group 1","np":2,"cix":2,"bm":0,"ix":1,"mn":"ADBE Vector Group","hd":false}],"ip":0,"op":503,"st":0,"bm":0},{"ddd":0,"ind":51,"ty":4,"nm":"la1-10 Outlines","parent":1,"sr":1,"ks":{"o":{"a":0,"k":100,"ix":11},"r":{"a":0,"k":0,"ix":10},"p":{"a":0,"k":[44.907,315.484,0],"ix":2},"a":{"a":0,"k":[15.513,15.513,0],"ix":1},"s":{"a":1,"k":[{"i":{"x":[0.833,0.833,0.833],"y":[0.833,0.833,0.833]},"o":{"x":[0.167,0.167,0.167],"y":[0.167,0.167,0.167]},"t":10,"s":[136.986,133.333,100]},{"i":{"x":[0.833,0.833,0.833],"y":[0.833,0.833,0.833]},"o":{"x":[0.167,0.167,0.167],"y":[0.167,0.167,0.167]},"t":15,"s":[160,155.733,100]},{"i":{"x":[0.833,0.833,0.833],"y":[0.833,0.833,0.833]},"o":{"x":[0.167,0.167,0.167],"y":[0.167,0.167,0.167]},"t":37,"s":[160,155.733,100]},{"t":42,"s":[136.986,133.333,100]}],"ix":6}},"ao":0,"shapes":[{"ty":"gr","it":[{"ind":0,"ty":"sh","ix":1,"ks":{"a":0,"k":{"i":[[0,0],[0,0],[0,0],[0,0]],"o":[[0,0],[0,0],[0,0],[0,0]],"v":[[11.356,11.356],[-11.356,11.356],[-11.356,-11.356],[11.356,-11.356]],"c":true},"ix":2},"nm":"Path 1","mn":"ADBE Vector Shape - Group","hd":false},{"ty":"st","c":{"a":0,"k":[0,0,0,1],"ix":3},"o":{"a":0,"k":100,"ix":4},"w":{"a":0,"k":1.663,"ix":5},"lc":1,"lj":1,"ml":10,"bm":0,"nm":"Stroke 1","mn":"ADBE Vector Graphic - Stroke","hd":false},{"ty":"fl","c":{"a":0,"k":[1,1,1,1],"ix":4},"o":{"a":0,"k":100,"ix":5},"r":1,"bm":0,"nm":"Fill 1","mn":"ADBE Vector Graphic - Fill","hd":false},{"ty":"tr","p":{"a":0,"k":[15.513,15.513],"ix":2},"a":{"a":0,"k":[0,0],"ix":1},"s":{"a":0,"k":[100,100],"ix":3},"r":{"a":0,"k":0,"ix":6},"o":{"a":0,"k":100,"ix":7},"sk":{"a":0,"k":0,"ix":4},"sa":{"a":0,"k":0,"ix":5},"nm":"Transform"}],"nm":"Group 1","np":3,"cix":2,"bm":0,"ix":1,"mn":"ADBE Vector Group","hd":false}],"ip":0,"op":503,"st":0,"bm":0},{"ddd":0,"ind":53,"ty":4,"nm":"la1-07 Outlines","parent":1,"sr":1,"ks":{"o":{"a":0,"k":100,"ix":11},"r":{"a":0,"k":0,"ix":10},"p":{"a":0,"k":[46.277,248.817,0],"ix":2},"a":{"a":0,"k":[15.513,15.513,0],"ix":1},"s":{"a":1,"k":[{"i":{"x":[0.833,0.833,0.833],"y":[0.833,0.833,0.833]},"o":{"x":[0.167,0.167,0.167],"y":[0.167,0.167,0.167]},"t":5,"s":[136.986,133.333,100]},{"i":{"x":[0.833,0.833,0.833],"y":[0.833,0.833,0.833]},"o":{"x":[0.167,0.167,0.167],"y":[0.167,0.167,0.167]},"t":10,"s":[160,155.733,100]},{"i":{"x":[0.833,0.833,0.833],"y":[0.833,0.833,0.833]},"o":{"x":[0.167,0.167,0.167],"y":[0.167,0.167,0.167]},"t":15,"s":[136.986,133.333,100]},{"i":{"x":[0.833,0.833,0.833],"y":[0.833,0.833,0.833]},"o":{"x":[0.167,0.167,0.167],"y":[0.167,0.167,0.167]},"t":37,"s":[136.986,133.333,100]},{"i":{"x":[0.833,0.833,0.833],"y":[0.833,0.833,0.833]},"o":{"x":[0.167,0.167,0.167],"y":[0.167,0.167,0.167]},"t":42,"s":[160,155.733,100]},{"i":{"x":[0.833,0.833,0.833],"y":[0.833,0.833,0.833]},"o":{"x":[0.167,0.167,0.167],"y":[0.167,0.167,0.167]},"t":64,"s":[160,155.733,100]},{"i":{"x":[0.833,0.833,0.833],"y":[0.833,0.833,0.833]},"o":{"x":[0.167,0.167,0.167],"y":[0.167,0.167,0.167]},"t":68,"s":[180,175.2,100]},{"i":{"x":[0.833,0.833,0.833],"y":[0.833,0.833,0.833]},"o":{"x":[0.167,0.167,0.167],"y":[0.167,0.167,0.167]},"t":77,"s":[160,155.733,100]},{"i":{"x":[0.833,0.833,0.833],"y":[0.833,0.833,0.833]},"o":{"x":[0.167,0.167,0.167],"y":[0.167,0.167,0.167]},"t":83,"s":[160,155.733,100]},{"t":87,"s":[136.986,133.333,100]}],"ix":6}},"ao":0,"shapes":[{"ty":"gr","it":[{"ind":0,"ty":"sh","ix":1,"ks":{"a":0,"k":{"i":[[0,0],[0,0],[0,0],[0,0]],"o":[[0,0],[0,0],[0,0],[0,0]],"v":[[11.356,11.356],[-11.356,11.356],[-11.356,-11.356],[11.356,-11.356]],"c":true},"ix":2},"nm":"Path 1","mn":"ADBE Vector Shape - Group","hd":false},{"ty":"st","c":{"a":0,"k":[0,0,0,1],"ix":3},"o":{"a":0,"k":100,"ix":4},"w":{"a":0,"k":1.663,"ix":5},"lc":1,"lj":1,"ml":10,"bm":0,"nm":"Stroke 1","mn":"ADBE Vector Graphic - Stroke","hd":false},{"ty":"fl","c":{"a":0,"k":[1,1,1,1],"ix":4},"o":{"a":0,"k":100,"ix":5},"r":1,"bm":0,"nm":"Fill 1","mn":"ADBE Vector Graphic - Fill","hd":false},{"ty":"tr","p":{"a":0,"k":[15.513,15.513],"ix":2},"a":{"a":0,"k":[0,0],"ix":1},"s":{"a":0,"k":[100,100],"ix":3},"r":{"a":0,"k":0,"ix":6},"o":{"a":0,"k":100,"ix":7},"sk":{"a":0,"k":0,"ix":4},"sa":{"a":0,"k":0,"ix":5},"nm":"Transform"}],"nm":"Group 1","np":3,"cix":2,"bm":0,"ix":1,"mn":"ADBE Vector Group","hd":false}],"ip":0,"op":503,"st":0,"bm":0},{"ddd":0,"ind":55,"ty":4,"nm":"la1-04 Outlines","parent":1,"sr":1,"ks":{"o":{"a":0,"k":100,"ix":11},"r":{"a":0,"k":0,"ix":10},"p":{"a":0,"k":[44.907,182.151,0],"ix":2},"a":{"a":0,"k":[15.513,15.513,0],"ix":1},"s":{"a":1,"k":[{"i":{"x":[0.833,0.833,0.833],"y":[0.833,0.833,0.833]},"o":{"x":[0.167,0.167,0.167],"y":[0.167,0.167,0.167]},"t":0,"s":[136.986,133.333,100]},{"i":{"x":[0.833,0.833,0.833],"y":[0.833,0.833,0.833]},"o":{"x":[0.167,0.167,0.167],"y":[0.167,0.167,0.167]},"t":5,"s":[160,155.733,100]},{"t":10,"s":[136.986,133.333,100]}],"ix":6}},"ao":0,"shapes":[{"ty":"gr","it":[{"ind":0,"ty":"sh","ix":1,"ks":{"a":0,"k":{"i":[[0,0],[0,0],[0,0],[0,0]],"o":[[0,0],[0,0],[0,0],[0,0]],"v":[[11.356,11.356],[-11.356,11.356],[-11.356,-11.356],[11.356,-11.356]],"c":true},"ix":2},"nm":"Path 1","mn":"ADBE Vector Shape - Group","hd":false},{"ty":"st","c":{"a":0,"k":[0,0,0,1],"ix":3},"o":{"a":0,"k":100,"ix":4},"w":{"a":0,"k":1.663,"ix":5},"lc":1,"lj":1,"ml":10,"bm":0,"nm":"Stroke 1","mn":"ADBE Vector Graphic - Stroke","hd":false},{"ty":"fl","c":{"a":0,"k":[1,1,1,1],"ix":4},"o":{"a":0,"k":100,"ix":5},"r":1,"bm":0,"nm":"Fill 1","mn":"ADBE Vector Graphic - Fill","hd":false},{"ty":"tr","p":{"a":0,"k":[15.513,15.513],"ix":2},"a":{"a":0,"k":[0,0],"ix":1},"s":{"a":0,"k":[100,100],"ix":3},"r":{"a":0,"k":0,"ix":6},"o":{"a":0,"k":100,"ix":7},"sk":{"a":0,"k":0,"ix":4},"sa":{"a":0,"k":0,"ix":5},"nm":"Transform"}],"nm":"Group 1","np":3,"cix":2,"bm":0,"ix":1,"mn":"ADBE Vector Group","hd":false}],"ip":0,"op":503,"st":0,"bm":0},{"ddd":0,"ind":57,"ty":4,"nm":"la1-03 Outlines","parent":1,"sr":1,"ks":{"o":{"a":0,"k":100,"ix":11},"r":{"a":0,"k":0,"ix":10},"p":{"a":0,"k":[190.391,536.409,0],"ix":2},"a":{"a":0,"k":[38.564,12.88,0],"ix":1},"s":{"a":0,"k":[136.986,133.333,100],"ix":6}},"ao":0,"shapes":[{"ty":"gr","it":[{"ind":0,"ty":"sh","ix":1,"ks":{"a":0,"k":{"i":[[0,0],[0,0]],"o":[[0,0],[0,0]],"v":[[12.88,12.88],[64.248,12.88]],"c":false},"ix":2},"nm":"Path 1","mn":"ADBE Vector Shape - Group","hd":false},{"ty":"st","c":{"a":0,"k":[0,0,0,1],"ix":3},"o":{"a":0,"k":100,"ix":4},"w":{"a":0,"k":5.152,"ix":5},"lc":1,"lj":1,"ml":10,"bm":0,"nm":"Stroke 1","mn":"ADBE Vector Graphic - Stroke","hd":false},{"ty":"tr","p":{"a":0,"k":[0,0],"ix":2},"a":{"a":0,"k":[0,0],"ix":1},"s":{"a":0,"k":[100,100],"ix":3},"r":{"a":0,"k":0,"ix":6},"o":{"a":0,"k":100,"ix":7},"sk":{"a":0,"k":0,"ix":4},"sa":{"a":0,"k":0,"ix":5},"nm":"Transform"}],"nm":"Group 1","np":2,"cix":2,"bm":0,"ix":1,"mn":"ADBE Vector Group","hd":false}],"ip":0,"op":503,"st":0,"bm":0},{"ddd":0,"ind":59,"ty":4,"nm":"la1-02 Outlines","parent":1,"sr":1,"ks":{"o":{"a":0,"k":100,"ix":11},"r":{"a":0,"k":0,"ix":10},"p":{"a":0,"k":[186.215,88.245,0],"ix":2},"a":{"a":0,"k":[142.85,46.756,0],"ix":1},"s":{"a":0,"k":[136.986,133.333,100],"ix":6}},"ao":0,"shapes":[{"ty":"gr","it":[{"ind":0,"ty":"sh","ix":1,"ks":{"a":0,"k":{"i":[[0,2.331],[2.403,0],[0.766,-0.676],[2.118,0],[0.293,-2.118],[1.092,0],[0,-2.403],[-2.402,0],[-0.013,0],[0,0],[0,0],[0,0]],"o":[[0,-2.402],[-1.102,0],[-0.389,-2.004],[-2.199,0],[-0.764,-0.664],[-2.402,0],[0,2.402],[0.014,0],[0,0],[0,0],[0,0],[2.303,-0.111]],"v":[[11.482,-0.913],[7.131,-5.262],[4.267,-4.163],[0,-7.682],[-4.29,-3.927],[-7.132,-5.007],[-11.482,-0.658],[-7.132,3.693],[-7.092,3.689],[-7.092,7.682],[7.341,7.682],[7.341,3.417]],"c":true},"ix":2},"nm":"Path 1","mn":"ADBE Vector Shape - Group","hd":false},{"ty":"st","c":{"a":0,"k":[0,0,0,1],"ix":3},"o":{"a":0,"k":100,"ix":4},"w":{"a":0,"k":1.663,"ix":5},"lc":1,"lj":1,"ml":10,"bm":0,"nm":"Stroke 1","mn":"ADBE Vector Graphic - Stroke","hd":false},{"ty":"tr","p":{"a":0,"k":[39.814,11.84],"ix":2},"a":{"a":0,"k":[0,0],"ix":1},"s":{"a":0,"k":[100,100],"ix":3},"r":{"a":0,"k":0,"ix":6},"o":{"a":0,"k":100,"ix":7},"sk":{"a":0,"k":0,"ix":4},"sa":{"a":0,"k":0,"ix":5},"nm":"Transform"}],"nm":"Group 1","np":2,"cix":2,"bm":0,"ix":1,"mn":"ADBE Vector Group","hd":false},{"ty":"gr","it":[{"ind":0,"ty":"sh","ix":1,"ks":{"a":0,"k":{"i":[[0,-4.462],[7.132,0],[0,7.131],[-3.444,2.323],[0,0]],"o":[[0,7.131],[-7.131,0],[0,-4.462],[0,0],[3.444,2.323]],"v":[[12.909,-1.095],[-0.001,11.813],[-12.908,-1.095],[-7.202,-11.813],[7.202,-11.813]],"c":true},"ix":2},"nm":"Path 1","mn":"ADBE Vector Shape - Group","hd":false},{"ty":"st","c":{"a":0,"k":[0,0,0,1],"ix":3},"o":{"a":0,"k":100,"ix":4},"w":{"a":0,"k":1.663,"ix":5},"lc":1,"lj":1,"ml":10,"bm":0,"nm":"Stroke 1","mn":"ADBE Vector Graphic - Stroke","hd":false},{"ty":"tr","p":{"a":0,"k":[40.161,31.38],"ix":2},"a":{"a":0,"k":[0,0],"ix":1},"s":{"a":0,"k":[100,100],"ix":3},"r":{"a":0,"k":0,"ix":6},"o":{"a":0,"k":100,"ix":7},"sk":{"a":0,"k":0,"ix":4},"sa":{"a":0,"k":0,"ix":5},"nm":"Transform"}],"nm":"Group 2","np":2,"cix":2,"bm":0,"ix":2,"mn":"ADBE Vector Group","hd":false},{"ty":"gr","it":[{"ind":0,"ty":"sh","ix":1,"ks":{"a":0,"k":{"i":[[0,0],[0,0],[0,0],[0,0]],"o":[[0,0],[0,0],[0,0],[0,0]],"v":[[1.495,0.753],[-1.495,0.753],[-1.495,-0.753],[1.495,-0.753]],"c":true},"ix":2},"nm":"Path 1","mn":"ADBE Vector Shape - Group","hd":false},{"ty":"fl","c":{"a":0,"k":[0,0,0,1],"ix":4},"o":{"a":0,"k":100,"ix":5},"r":1,"bm":0,"nm":"Fill 1","mn":"ADBE Vector Graphic - Fill","hd":false},{"ty":"tr","p":{"a":0,"k":[39.836,36.515],"ix":2},"a":{"a":0,"k":[0,0],"ix":1},"s":{"a":0,"k":[100,100],"ix":3},"r":{"a":0,"k":0,"ix":6},"o":{"a":0,"k":100,"ix":7},"sk":{"a":0,"k":0,"ix":4},"sa":{"a":0,"k":0,"ix":5},"nm":"Transform"}],"nm":"Group 3","np":2,"cix":2,"bm":0,"ix":3,"mn":"ADBE Vector Group","hd":false},{"ty":"gr","it":[{"ind":0,"ty":"sh","ix":1,"ks":{"a":0,"k":{"i":[[0,0],[-2.362,2.153],[-3.622,0.085]],"o":[[3.729,-0.198],[2.683,2.228],[0,0]],"v":[[-9.339,1.498],[-0.07,-1.583],[9.339,1.498]],"c":false},"ix":2},"nm":"Path 1","mn":"ADBE Vector Shape - Group","hd":false},{"ty":"st","c":{"a":0,"k":[0,0,0,1],"ix":3},"o":{"a":0,"k":100,"ix":4},"w":{"a":0,"k":1.663,"ix":5},"lc":1,"lj":1,"ml":10,"bm":0,"nm":"Stroke 1","mn":"ADBE Vector Graphic - Stroke","hd":false},{"ty":"tr","p":{"a":0,"k":[39.895,30.904],"ix":2},"a":{"a":0,"k":[0,0],"ix":1},"s":{"a":0,"k":[100,100],"ix":3},"r":{"a":0,"k":0,"ix":6},"o":{"a":0,"k":100,"ix":7},"sk":{"a":0,"k":0,"ix":4},"sa":{"a":0,"k":0,"ix":5},"nm":"Transform"}],"nm":"Group 4","np":2,"cix":2,"bm":0,"ix":4,"mn":"ADBE Vector Group","hd":false},{"ty":"gr","it":[{"ind":0,"ty":"sh","ix":1,"ks":{"a":0,"k":{"i":[[0,-1.036],[1.036,0],[0,1.036],[-1.036,0]],"o":[[0,1.036],[-1.036,0],[0,-1.036],[1.036,0]],"v":[[1.876,-0.001],[0,1.876],[-1.876,-0.001],[0,-1.876]],"c":true},"ix":2},"nm":"Path 1","mn":"ADBE Vector Shape - Group","hd":false},{"ty":"st","c":{"a":0,"k":[0,0,0,1],"ix":3},"o":{"a":0,"k":100,"ix":4},"w":{"a":0,"k":1.663,"ix":5},"lc":1,"lj":1,"ml":10,"bm":0,"nm":"Stroke 1","mn":"ADBE Vector Graphic - Stroke","hd":false},{"ty":"tr","p":{"a":0,"k":[43.211,23.962],"ix":2},"a":{"a":0,"k":[0,0],"ix":1},"s":{"a":0,"k":[100,100],"ix":3},"r":{"a":0,"k":0,"ix":6},"o":{"a":0,"k":100,"ix":7},"sk":{"a":0,"k":0,"ix":4},"sa":{"a":0,"k":0,"ix":5},"nm":"Transform"}],"nm":"Group 5","np":2,"cix":2,"bm":0,"ix":5,"mn":"ADBE Vector Group","hd":false},{"ty":"gr","it":[{"ind":0,"ty":"sh","ix":1,"ks":{"a":0,"k":{"i":[[0,-1.036],[1.036,0],[0,1.036],[-1.037,0]],"o":[[0,1.036],[-1.037,0],[0,-1.036],[1.036,0]],"v":[[1.876,-0.001],[0.001,1.876],[-1.876,-0.001],[0.001,-1.876]],"c":true},"ix":2},"nm":"Path 1","mn":"ADBE Vector Shape - Group","hd":false},{"ty":"st","c":{"a":0,"k":[0,0,0,1],"ix":3},"o":{"a":0,"k":100,"ix":4},"w":{"a":0,"k":1.663,"ix":5},"lc":1,"lj":1,"ml":10,"bm":0,"nm":"Stroke 1","mn":"ADBE Vector Graphic - Stroke","hd":false},{"ty":"tr","p":{"a":0,"k":[37.488,23.962],"ix":2},"a":{"a":0,"k":[0,0],"ix":1},"s":{"a":0,"k":[100,100],"ix":3},"r":{"a":0,"k":0,"ix":6},"o":{"a":0,"k":100,"ix":7},"sk":{"a":0,"k":0,"ix":4},"sa":{"a":0,"k":0,"ix":5},"nm":"Transform"}],"nm":"Group 6","np":2,"cix":2,"bm":0,"ix":6,"mn":"ADBE Vector Group","hd":false},{"ty":"gr","it":[{"ind":0,"ty":"sh","ix":1,"ks":{"a":0,"k":{"i":[[0,0],[0,0],[0,-0.363],[0,0],[0,0],[0,0],[-0.363,0],[0,0],[0,0],[0,0],[0,0],[0,-0.363],[0,0],[0,0],[0,0],[-0.337,0.034]],"o":[[0,0],[0.363,0],[0,0],[0,0],[0,0],[0,-0.363],[0,0],[0,0],[0,0],[0,0],[0.362,0],[0,0],[0,0],[0,0],[-0.001,-0.338],[0,0]],"v":[[-4.154,3.274],[4.113,3.274],[4.77,3.931],[4.77,14.684],[10.54,14.684],[10.54,0.014],[11.198,-0.643],[14.273,-0.643],[-0.027,-14.404],[-14.327,-0.643],[-11.238,-0.643],[-10.581,0.014],[-10.581,14.684],[-4.746,14.684],[-4.746,3.957],[-4.154,3.3]],"c":true},"ix":2},"nm":"Path 1","mn":"ADBE Vector Shape - Group","hd":false},{"ind":1,"ty":"sh","ix":2,"ks":{"a":0,"k":{"i":[[0,0],[0,0.363],[0,0],[0,0],[0,0],[0.364,0],[0,0],[0,0.363],[0,0],[0,0],[0.002,0.363],[-0.13,0.125],[0,0],[-0.265,-0.239],[0,0],[0.252,-0.261],[0.18,0.001],[0,0],[0,0],[0.362,0]],"o":[[-0.363,0],[0,0],[0,0],[0,0],[0,0.363],[0,0],[-0.364,0],[0,0],[0,0],[-0.363,0.002],[-0.001,-0.18],[0,0],[0.265,-0.239],[0,0],[0.261,0.252],[-0.125,0.13],[0,0],[0,0],[0,0.363],[0,0]],"v":[[4.113,15.997],[3.456,15.34],[3.456,4.615],[-3.431,4.615],[-3.431,15.366],[-4.089,16.023],[-11.238,16.023],[-11.896,15.366],[-11.896,0.671],[-15.957,0.671],[-16.618,0.018],[-16.417,-0.458],[-0.487,-15.785],[0.446,-15.785],[16.35,-0.458],[16.367,0.47],[15.89,0.671],[11.855,0.671],[11.855,15.34],[11.198,15.997]],"c":true},"ix":2},"nm":"Path 2","mn":"ADBE Vector Shape - Group","hd":false},{"ty":"mm","mm":1,"nm":"Merge Paths 1","mn":"ADBE Vector Filter - Merge","hd":false},{"ty":"fl","c":{"a":0,"k":[0,0,0,1],"ix":4},"o":{"a":0,"k":100,"ix":5},"r":1,"bm":0,"nm":"Fill 1","mn":"ADBE Vector Graphic - Fill","hd":false},{"ty":"tr","p":{"a":0,"k":[197.862,22.78],"ix":2},"a":{"a":0,"k":[0,0],"ix":1},"s":{"a":0,"k":[100,100],"ix":3},"r":{"a":0,"k":0,"ix":6},"o":{"a":0,"k":100,"ix":7},"sk":{"a":0,"k":0,"ix":4},"sa":{"a":0,"k":0,"ix":5},"nm":"Transform"}],"nm":"Group 7","np":4,"cix":2,"bm":0,"ix":7,"mn":"ADBE Vector Group","hd":false},{"ty":"gr","it":[{"ind":0,"ty":"sh","ix":1,"ks":{"a":0,"k":{"i":[[0,0],[0,0],[0,0],[0,0]],"o":[[0,0],[0,0],[0,0],[0,0]],"v":[[36.559,3.884],[-36.559,3.884],[-36.559,-3.884],[36.559,-3.884]],"c":true},"ix":2},"nm":"Path 1","mn":"ADBE Vector Shape - Group","hd":false},{"ty":"fl","c":{"a":0,"k":[0.8,0.8,0.8,1],"ix":4},"o":{"a":0,"k":100,"ix":5},"r":1,"bm":0,"nm":"Fill 1","mn":"ADBE Vector Graphic - Fill","hd":false},{"ty":"tr","p":{"a":0,"k":[119.091,70.921],"ix":2},"a":{"a":0,"k":[0,0],"ix":1},"s":{"a":0,"k":[100,100],"ix":3},"r":{"a":0,"k":0,"ix":6},"o":{"a":0,"k":100,"ix":7},"sk":{"a":0,"k":0,"ix":4},"sa":{"a":0,"k":0,"ix":5},"nm":"Transform"}],"nm":"Group 8","np":2,"cix":2,"bm":0,"ix":8,"mn":"ADBE Vector Group","hd":false},{"ty":"gr","it":[{"ind":0,"ty":"sh","ix":1,"ks":{"a":0,"k":{"i":[[0,0],[0,0],[0,0],[0,0]],"o":[[0,0],[0,0],[0,0],[0,0]],"v":[[25.282,3.884],[-25.282,3.884],[-25.282,-3.884],[25.282,-3.884]],"c":true},"ix":2},"nm":"Path 1","mn":"ADBE Vector Shape - Group","hd":false},{"ty":"fl","c":{"a":0,"k":[0.8,0.8,0.8,1],"ix":4},"o":{"a":0,"k":100,"ix":5},"r":1,"bm":0,"nm":"Fill 1","mn":"ADBE Vector Graphic - Fill","hd":false},{"ty":"tr","p":{"a":0,"k":[51.406,70.921],"ix":2},"a":{"a":0,"k":[0,0],"ix":1},"s":{"a":0,"k":[100,100],"ix":3},"r":{"a":0,"k":0,"ix":6},"o":{"a":0,"k":100,"ix":7},"sk":{"a":0,"k":0,"ix":4},"sa":{"a":0,"k":0,"ix":5},"nm":"Transform"}],"nm":"Group 9","np":2,"cix":2,"bm":0,"ix":9,"mn":"ADBE Vector Group","hd":false},{"ty":"gr","it":[{"ind":0,"ty":"sh","ix":1,"ks":{"a":0,"k":{"i":[[0,0],[0,0],[0,0],[0,0]],"o":[[0,0],[0,0],[0,0],[0,0]],"v":[[37.085,5.234],[-37.085,5.234],[-37.085,-5.234],[37.085,-5.234]],"c":true},"ix":2},"nm":"Path 1","mn":"ADBE Vector Shape - Group","hd":false},{"ty":"fl","c":{"a":0,"k":[0.8,0.8,0.8,1],"ix":4},"o":{"a":0,"k":100,"ix":5},"r":1,"bm":0,"nm":"Fill 1","mn":"ADBE Vector Graphic - Fill","hd":false},{"ty":"tr","p":{"a":0,"k":[105.206,26.073],"ix":2},"a":{"a":0,"k":[0,0],"ix":1},"s":{"a":0,"k":[100,100],"ix":3},"r":{"a":0,"k":0,"ix":6},"o":{"a":0,"k":100,"ix":7},"sk":{"a":0,"k":0,"ix":4},"sa":{"a":0,"k":0,"ix":5},"nm":"Transform"}],"nm":"Group 10","np":2,"cix":2,"bm":0,"ix":10,"mn":"ADBE Vector Group","hd":false},{"ty":"gr","it":[{"ind":0,"ty":"sh","ix":1,"ks":{"a":0,"k":{"i":[[0,0],[0,0],[0,0],[0,0]],"o":[[0,0],[0,0],[0,0],[0,0]],"v":[[1.109,7.134],[-1.046,7.134],[-1.046,4.966],[1.109,4.966]],"c":true},"ix":2},"nm":"Path 1","mn":"ADBE Vector Shape - Group","hd":false},{"ind":1,"ty":"sh","ix":2,"ks":{"a":0,"k":{"i":[[0,0]],"o":[[0,0]],"v":[[1.109,4.965]],"c":false},"ix":2},"nm":"Path 2","mn":"ADBE Vector Shape - Group","hd":false},{"ind":2,"ty":"sh","ix":3,"ks":{"a":0,"k":{"i":[[-0.202,0.596],[-0.384,0.436],[-0.525,0.224],[-0.626,-0.007],[-0.535,-0.179],[-0.375,-0.336],[-0.189,-0.465],[0.011,-0.568],[0.103,-0.352],[0.162,-0.272],[0.202,-0.22],[0,0],[0,0],[0.165,-0.23],[0.095,-0.263],[-0.004,-0.308],[0,0],[0,0],[0,0],[-0.186,0.435],[-0.261,0.312],[-0.283,0.257],[-0.244,0.282],[-0.144,0.334],[0.034,0.416],[0.429,0.454],[0.613,-0.032],[0.379,-0.173],[0.229,-0.288],[0.093,-0.369],[-0.005,-0.425],[0,0]],"o":[[0.187,-0.551],[0.379,-0.427],[0.577,-0.243],[0.564,-0.008],[0.476,0.162],[0.371,0.34],[0.211,0.528],[0.004,0.367],[-0.093,0.303],[-0.155,0.254],[0,0],[0,0],[-0.2,0.2],[-0.161,0.228],[-0.103,0.29],[0,0],[0,0],[0,0],[0.014,-0.473],[0.167,-0.371],[0.247,-0.291],[0.277,-0.249],[0.239,-0.274],[0.151,-0.389],[-0.013,-0.624],[-0.449,-0.418],[-0.416,-0.01],[-0.33,0.164],[-0.234,0.301],[-0.105,0.412],[0,0],[-0.021,-0.628]],"v":[[-3.941,-4.285],[-3.076,-5.781],[-1.703,-6.769],[0.122,-7.126],[1.783,-6.866],[3.073,-6.111],[3.923,-4.889],[4.226,-3.228],[4.075,-2.144],[3.691,-1.279],[3.155,-0.566],[2.538,0.079],[1.92,0.669],[1.37,1.315],[0.986,2.056],[0.836,2.961],[0.836,3.716],[-0.77,3.716],[-0.77,2.797],[-0.468,1.424],[0.176,0.395],[0.973,-0.429],[1.755,-1.225],[2.331,-2.144],[2.51,-3.366],[1.824,-5.04],[0.163,-5.644],[-1.046,-5.397],[-1.895,-4.711],[-2.391,-3.695],[-2.541,-2.433],[-4.215,-2.433]],"c":true},"ix":2},"nm":"Path 3","mn":"ADBE Vector Shape - Group","hd":false},{"ty":"mm","mm":1,"nm":"Merge Paths 1","mn":"ADBE Vector Filter - Merge","hd":false},{"ty":"fl","c":{"a":0,"k":[0,0,0,1],"ix":4},"o":{"a":0,"k":100,"ix":5},"r":1,"bm":0,"nm":"Fill 1","mn":"ADBE Vector Graphic - Fill","hd":false},{"ty":"tr","p":{"a":0,"k":[242.511,22.799],"ix":2},"a":{"a":0,"k":[0,0],"ix":1},"s":{"a":0,"k":[100,100],"ix":3},"r":{"a":0,"k":0,"ix":6},"o":{"a":0,"k":100,"ix":7},"sk":{"a":0,"k":0,"ix":4},"sa":{"a":0,"k":0,"ix":5},"nm":"Transform"}],"nm":"Group 11","np":5,"cix":2,"bm":0,"ix":11,"mn":"ADBE Vector Group","hd":false},{"ty":"gr","it":[{"ind":0,"ty":"sh","ix":1,"ks":{"a":0,"k":{"i":[[0,0],[0.061,-8.338],[-8.338,-0.061],[-0.06,8.337],[0.001,0.073],[8.295,0.06]],"o":[[-8.338,-0.06],[-0.06,8.337],[8.338,0.06],[0.001,-0.074],[0,-8.296],[0,0]],"v":[[0.14,-14.988],[-15.067,0],[-0.079,15.206],[15.127,0.219],[15.127,0],[0.14,-15.097]],"c":true},"ix":2},"nm":"Path 1","mn":"ADBE Vector Shape - Group","hd":false},{"ind":1,"ty":"sh","ix":2,"ks":{"a":0,"k":{"i":[[9.053,-0.061],[0.06,9.095],[-9.095,0.06],[-0.06,-9.096],[0,-0.037]],"o":[[-9.096,0.06],[-0.061,-9.096],[9.096,-0.061],[0,0.037],[0,9.053]],"v":[[0.14,16.47],[-16.439,0.11],[-0.08,-16.469],[16.499,-0.11],[16.5,0]],"c":true},"ix":2},"nm":"Path 2","mn":"ADBE Vector Shape - Group","hd":false},{"ty":"mm","mm":1,"nm":"Merge Paths 1","mn":"ADBE Vector Filter - Merge","hd":false},{"ty":"fl","c":{"a":0,"k":[0,0,0,1],"ix":4},"o":{"a":0,"k":100,"ix":5},"r":1,"bm":0,"nm":"Fill 1","mn":"ADBE Vector Graphic - Fill","hd":false},{"ty":"tr","p":{"a":0,"k":[242.383,22.81],"ix":2},"a":{"a":0,"k":[0,0],"ix":1},"s":{"a":0,"k":[100,100],"ix":3},"r":{"a":0,"k":0,"ix":6},"o":{"a":0,"k":100,"ix":7},"sk":{"a":0,"k":0,"ix":4},"sa":{"a":0,"k":0,"ix":5},"nm":"Transform"}],"nm":"Group 12","np":4,"cix":2,"bm":0,"ix":12,"mn":"ADBE Vector Group","hd":false},{"ty":"gr","it":[{"ind":0,"ty":"sh","ix":1,"ks":{"a":0,"k":{"i":[[0,0],[0,0]],"o":[[0,0],[0,0]],"v":[[7.287,86.224],[278.412,86.224]],"c":false},"ix":2},"nm":"Path 1","mn":"ADBE Vector Shape - Group","hd":false},{"ty":"st","c":{"a":0,"k":[1,0.941000007181,0.250999989229,1],"ix":3},"o":{"a":0,"k":100,"ix":4},"w":{"a":0,"k":2.915,"ix":5},"lc":1,"lj":1,"ml":10,"bm":0,"nm":"Stroke 1","mn":"ADBE Vector Graphic - Stroke","hd":false},{"ty":"tr","p":{"a":0,"k":[0,0],"ix":2},"a":{"a":0,"k":[0,0],"ix":1},"s":{"a":0,"k":[100,100],"ix":3},"r":{"a":0,"k":0,"ix":6},"o":{"a":0,"k":100,"ix":7},"sk":{"a":0,"k":0,"ix":4},"sa":{"a":0,"k":0,"ix":5},"nm":"Transform"}],"nm":"Group 13","np":2,"cix":2,"bm":0,"ix":13,"mn":"ADBE Vector Group","hd":false}],"ip":0,"op":503,"st":0,"bm":0},{"ddd":0,"ind":61,"ty":4,"nm":"la1-01 Outlines","sr":1,"ks":{"o":{"a":0,"k":100,"ix":11},"r":{"a":0,"k":0,"ix":10},"p":{"a":0,"k":[135.372,215.009,0],"ix":2},"a":{"a":0,"k":[135.575,215.259,0],"ix":1},"s":{"a":0,"k":[100,100,100],"ix":6}},"ao":0,"shapes":[{"ty":"gr","it":[{"ind":0,"ty":"sh","ix":1,"ks":{"a":0,"k":{"i":[[0,0],[0,0],[4.069,0],[0,0],[0,4.069],[0,0]],"o":[[0,0],[0,4.069],[0,0],[-4.069,0],[0,0],[0,0]],"v":[[135.325,-31.59],[135.325,24.24],[127.958,31.608],[-127.958,31.608],[-135.325,24.24],[-135.325,-31.59]],"c":true},"ix":2},"nm":"Path 1","mn":"ADBE Vector Shape - Group","hd":false},{"ty":"fl","c":{"a":0,"k":[1,0.941000007181,0.250999989229,1],"ix":4},"o":{"a":0,"k":100,"ix":5},"r":1,"bm":0,"nm":"Fill 1","mn":"ADBE Vector Graphic - Fill","hd":false},{"ty":"tr","p":{"a":0,"k":[135.575,398.66],"ix":2},"a":{"a":0,"k":[0,0],"ix":1},"s":{"a":0,"k":[100,100],"ix":3},"r":{"a":0,"k":0,"ix":6},"o":{"a":0,"k":100,"ix":7},"sk":{"a":0,"k":0,"ix":4},"sa":{"a":0,"k":0,"ix":5},"nm":"Transform"}],"nm":"Group 1","np":4,"cix":2,"bm":0,"ix":1,"mn":"ADBE Vector Group","hd":false},{"ty":"gr","it":[{"ind":0,"ty":"sh","ix":1,"ks":{"a":0,"k":{"i":[[0,-4.069],[0,0],[0,0],[0,0],[-4.069,0],[0,0]],"o":[[0,0],[0,0],[0,0],[0,-4.069],[0,0],[4.069,0]],"v":[[135.325,-176.133],[135.325,183.5],[-135.325,183.5],[-135.325,-176.133],[-127.958,-183.5],[127.958,-183.5]],"c":true},"ix":2},"nm":"Path 1","mn":"ADBE Vector Shape - Group","hd":false},{"ty":"fl","c":{"a":0,"k":[1,1,1,1],"ix":4},"o":{"a":0,"k":100,"ix":5},"r":1,"bm":0,"nm":"Fill 1","mn":"ADBE Vector Graphic - Fill","hd":false},{"ty":"tr","p":{"a":0,"k":[135.575,183.75],"ix":2},"a":{"a":0,"k":[0,0],"ix":1},"s":{"a":0,"k":[100,100],"ix":3},"r":{"a":0,"k":0,"ix":6},"o":{"a":0,"k":100,"ix":7},"sk":{"a":0,"k":0,"ix":4},"sa":{"a":0,"k":0,"ix":5},"nm":"Transform"}],"nm":"Group 2","np":2,"cix":2,"bm":0,"ix":2,"mn":"ADBE Vector Group","hd":false}],"ip":0,"op":503,"st":0,"bm":0}],"markers":[]}